Workbook

Sheet 使い方
A1: 実務型スライド 読み取り評価【上級】（5ファイル × 20問 ＝ 100問）
A3: ■ 対象ファイル
A4: ・06_新規出店計画.pptx（地図・バブルチャート・リンク・トリミング画像など、10枚）
A5: ・07_品質改善報告_8D.pptx（計器写真・スキャン文書・パレート図・管理図など、10枚）
A6: ・08_デジタル広告_効果検証.pptx（背景の透かし・ファネル・複合グラフ・埋め込みExcelなど、10枚）
A7: ・09_組織再編案.pptx（レイアウト上の版数・セクション・ベン図・親和図など、10枚）
A8: ・10_技術開発ロードマップ.pptx（対数軸・逆順軸・化学式・SVG画像など、10枚）
A10: ■ 進め方
A11: 1. ファイルごとのシートを開き、そのファイル全体（10枚）をLLMに入力する。
A12: 2. 『質問』列の文章をそのまま1問ずつ質問する。1問ごとに新しいセッションで、ファイルを入力し直すのが望ましい（前の回答がヒントになるのを防ぐ）。
A13: 3. 黄色セルに記入：判定（OK／部分／NG）、LLMの回答（要点）、備考。
A14: 4. 『集計』シートにファイル別・問題種別ごとの正答率が出る（OK=1点、部分=0.5点）。
... A21: ・『根拠』列は正解の出どころ（スライド番号と要素）。採点時の確認用で、LLMには見せない。

Sheet 06_新規出店計画
A1: 対象：06_新規出店計画.pptx（10枚）
A2: No. | B2: 出題スライド | C2: 問題種別 | D2: 質問（コピペ用） | E2: 正解 | F2: 判定基準 | G2: 根拠（採点用） | H2: 判定 | I2: LLMの回答 | J2: 備考 | K2: LLMの回答（生値） | L2: テストID
A3: 1 | B3: P2 | C3: 書式・文字装飾 | D3: 出店優先度が『高』とされているエリアをすべて答えてください。 | E3: 中央、湾岸 | F3: 正解の要素がすべて含まれる=OK／一部のみ=部分／誤り・スライドにない内容を断定=NG | G3: 【書式・色（地図）】P2 フリーフォームの塗り色＋凡例（評価点の数値はない） | H3: OK | I3: 中央、湾岸 | K3: 出店優先度が『高』とされているエリアは、次の2つです。 - 中央 - 湾岸 （スライド2「出店エリアの評価」より。いずれも評価点80以上） | L3: 06-01
A4: 2 | B4: P2 | C4: 書式・文字装飾 | D4: 中央エリアに隣接していて、優先度が『低』のエリアはどれですか？ | E4: 北、西 | F4: 正解の要素がすべて含まれる=OK／一部のみ=部分／誤り・スライドにない内容を断定=NG | G4: 【書式・色（地図）】P2 図形の色と隣接関係 | H4: OK | I4: 北、西（模式地図の配置から判断と明記） | K4: 中央エリアに隣接していて出店優先度が「低」のエリアは、**北**と**西**の2つです。 - 優先度が「低」（評価点60未満）なのは、北と西だけです（スライド2の表）。 - スライド2の模式地図では、北は左上、西は左中段、中央は中心にあります。どちらも中央のすぐ周りにあるので、中央に隣接していると読み取れます。 ※資料には隣接関係そのものは書かれていません。上の答えは、模式地図での「おおよその配置」から読み取ったものです。 | L4: 06-02
A5: 3 | B5: P3 | C5: グラフ | D5: 競合店舗数が最も少ない候補地はどこですか？店舗数も答えてください。 | E5: 南公園通り、2店 | F5: 正解の要素がすべて含まれる=OK／一部のみ=部分／誤り・スライドにない内容を断定=NG | G5: 【バブルチャート】P3 バブルのY値（ラベルなし） | H5: OK | I5: 南公園通り、2店 | K5: 競合店舗数が最も少ない候補地は「南公園通り」で、競合店舗数は2店です。 | L5: 06-03
A6: 4 | B6: P3 | C6: グラフ | D6: 推定年商が最も大きい候補地と、その金額を答えてください。 | E6: 中央駅前、96百万円 | F6: 正解の要素がすべて含まれる=OK／一部のみ=部分／誤り・スライドにない内容を断定=NG | G6: 【バブルチャート】P3 バブルの大きさ＝推定年商（P6の売上と一致） | H6: OK | I6: 中央駅前、96百万円 | K6: 推定年商が最も大きい候補地は「中央駅前」で、金額は96百万円（9,600万円）です。 | L6: 06-04
A7: 5 | B7: P3 | C7: グラフ | D7: 昼間人口が10万人未満で、かつ競合店舗数が5店未満の候補地をすべて答えてください。 | E7: 湾岸タワー（9.2万人・3店）、北大学前（6.3万人・4店）、南公園通り（5.1万人・2店） | F7: 正解の要素がすべて含まれる=OK／一部のみ=部分／誤り・スライドにない内容を断定=NG | G7: 【バブルチャート】P3 バブルのX・Y値 | H7: OK | I7: 湾岸タワー（9.2万人・3店）、南公園通り（5.1万人・2店）、北大学前（6.3万人・4店） | K7: 昼間人口が10万人未満で、かつ競合店舗数が5店未満の候補地は次の3か所です（スライド3のバブルチャートのデータより）。 | 候補地 | 昼間人口 | 競合店舗数 | | --- | --- | --- | | 湾岸タワー | 9.2万人 | 3店 | | 南公園通り | 5.1万人 | 2店 | | 北大学前 | 6.3万人 | 4店 | ※中央駅前は昼間人口18.5万人・競合12店、東口商店街は昼間人口7.4万人ですが競合が6店のため、どちらも条件に当てはまりません。 | L7: 06-05
A8: 6 | B8: P4 | C8: 画像 | D8: 現地写真に写っている看板に書かれている内容をすべて答えてください。 | E8: 「テナント募集」「1F 82㎡」のみ。（元画像の右側にある『工事予定 2027年3月まで』はトリミングで表示されていないため含めない） | F8: 表示部分の看板のみ=OK／トリミングで隠れた看板も挙げる=NG | G8: 【画像（トリミング）】P4 画像（右38%をトリミング） | H8: OK | I8: 「テナント募集」「1F 82㎡」のみ | J8: トリミング部分の看板は挙げていない（MDにもトリミング部分の記載なし） | K8: 現地写真（スライド4「候補地② 湾岸タワー1階 現地写真」）に写っている看板には、「テナント募集 1F 82㎡」と書かれています。 - 看板の形状：赤枠の看板 - 掲示場所：湾岸タワー1階のガラス張りの区画 - 記載内容：「テナント募集」「1F」「82㎡」（この82㎡はスライド8の店舗面積82m²と一致） なお、資料に記載されている看板の文字はこれだけです。 | L8: 06-06
A9: 7 | B9: P4 | C9: スライド上に見えない情報 | D9: 現地写真はいつ撮影されたものですか？ | E9: 2026年10月 | F9: 正解の要素がすべて含まれる=OK／一部のみ=部分／誤り・スライドにない内容を断定=NG | G9: 【代替テキスト】P4 画像の代替テキスト（スライド上には記載なし） | H9: OK | I9: 2026年10月（代替テキストより） | K9: 現地写真（スライド4、湾岸タワー1階の候補区画の外観）は、2026年10月に撮影されたものです（画像の代替テキスト「湾岸タワー1階の候補区画の外観（2026年10月撮影）」による）。 | L9: 06-07
A10: 8 | B10: P5 | C10: 画像 | D10: 地図上で、川の東側にある出店候補地をすべて答えてください。 | E10: ②湾岸タワー、④南公園通り | F10: 正解の要素がすべて含まれる=OK／一部のみ=部分／誤り・スライドにない内容を断定=NG | G10: 【画像（地図）】P5 地図画像のピン位置＋番号表 | H10: OK | I10: ②湾岸タワー、④南公園通り | K10: 地図上で川の東側にある出店候補地（青丸）は、次の2か所です。 - ② 湾岸タワー（地図の北東。線路より北で、川より東） - ④ 南公園通り（地図の南東。線路より南で、川より東） なお、①北大学前と⑤中央駅前は川の西側です。東口商店街は中央駅の東約2kmにありますが、地図の範囲外のため地図上には載っていません。 | L10: 06-08
A11: 9 | B11: P5 | C11: 画像 | D11: 既存店に最も近い出店候補地はどれですか？ | E11: ⑤中央駅前 | F11: 正解の要素がすべて含まれる=OK／一部のみ=部分／誤り・スライドにない内容を断定=NG | G11: 【画像（地図）】P5 地図画像のピン位置 | H11: OK | I11: ⑤中央駅前 | K11: 既存店（③モリノカフェ 中央店）に最も近い出店候補地は、**⑤中央駅前**です。 根拠（スライド5「候補地の位置」の地図より）： - ⑤中央駅前は中央駅のすぐ南、川より西にあります。 - ③モリノカフェ 中央店（既存店）は「⑤中央駅前のさらに南西」にあり、中央駅前の近くに位置しています。 - ほかの候補地はもっと離れています。①北大学前は地図の北西（線路より北）、②湾岸タワーは北東（線路より北・川より東）、④南公園通りは南東（川より東）にあり、東口商店街は地図の範囲外（中央駅の東約2km）です。 ※地図に距離の数値は書かれていないため、各地点の位置関係から判断しています。 | L11: 06-09
A12: 10 | B12: P6 | C12: 表 | D12: 収支シミュレーションで『優先候補』に分類されている候補地をすべて答えてください。 | E12: 湾岸タワー、中央駅前 | F12: 正解の要素がすべて含まれる=OK／一部のみ=部分／誤り・スライドにない内容を断定=NG | G12: 【結合セル】P6 縦に結合されたセル | H12: OK | I12: 湾岸タワー、中央駅前 | K12: 収支シミュレーション（スライド6）で「優先候補」に分類されている候補地は次の2つです。 - 湾岸タワー（投資回収3.8年で最短） - 中央駅前（年間売上96百万円で最大） | L12: 06-10
A13: 11 | B13: P6 | C13: 計算 | D13: 中央駅前の初期投資の合計はいくらですか？ | E13: 60百万円（内装42＋設備18） | F13: 数値が一致（丸め誤差±0.1まで）=OK／考え方は正しいが数値違い=部分／誤り=NG | G13: 【計算】P6 表（2段見出しの結合セル） | H13: OK | I13: 60百万円（内装42＋設備18） | K13: 中央駅前の初期投資の合計は **60百万円（6,000万円）** です。内訳は内装42百万円、設備18百万円です（スライド6「収支シミュレーション」、スライド10「決裁依頼」）。 | L13: 06-11
A14: 12 | B14: P6 | C14: 表 | D14: 投資回収年数が最も短い候補地と、その年数を答えてください。 | E14: 湾岸タワー、3.8年 | F14: 正解の要素がすべて含まれる=OK／一部のみ=部分／誤り・スライドにない内容を断定=NG | G14: 【表】P6 表 | H14: OK | I14: 湾岸タワー、3.8年 | K14: 投資回収年数が最も短い候補地は**湾岸タワー**で、その年数は**3.8年**です。 （スライド6「収支シミュレーション」より。初期投資合計54百万円÷年間営業利益14.2百万円で算出。次に短いのは中央駅前の4.5年です。） | L14: 06-12
A15: 13 | B15: P7 | C15: 図解・位置関係 | D15: 湾岸タワー店のスケジュールで、『内装工事』を始める前に完了している必要がある作業は何ですか？ | E15: 店舗設計 | F15: 正解の要素がすべて含まれる=OK／一部のみ=部分／誤り・スライドにない内容を断定=NG | G15: 【図解（依存関係）】P7 依存関係の矢印（コネクタ） | H15: OK | I15: 店舗設計 | J15: 物件契約も間接的に完了済みと補足（誤りではない） | K15: 『内装工事』を始める前に完了している必要があるのは「店舗設計」（2027年2月〜3月）です。 スライド7のスケジュールでは、矢印「店舗設計 → 内装工事」で示されるとおり、内装工事は店舗設計が終わってから開始します。なお、店舗設計はその前の「物件契約」（1月）が終わってから始まるため、結果として物件契約も内装工事の開始前に完了していることになります。 | L15: 06-13
A16: 14 | B16: P7 | C16: 書式・文字装飾 | D16: クリティカルパス上にあるタスクをすべて答えてください。 | E16: 物件契約、店舗設計、内装工事、開店準備（採用・研修は含まない） | F16: 正解の要素がすべて含まれる=OK／一部のみ=部分／誤り・スライドにない内容を断定=NG | G16: 【書式・色】P7 バーの色＋凡例 | H16: OK | I16: 物件契約、店舗設計、内装工事、開店準備（採用・研修は含まない） | K16: 湾岸タワー店の出店スケジュール（スライド7）で、クリティカルパス（赤）上にあるタスクは次の4つです。 1. 物件契約（2027年1月） 2. 店舗設計（2027年2月〜3月） 3. 内装工事（2027年4月〜5月） 4. 開店準備（2027年6月） この順に進んで、2027年7月1日の開店（マイルストーン）につながります。採用・研修（4月〜6月）は余裕のあるタスク（青）なので、クリティカルパスには含まれません。 | L16: 06-14
A17: 15 | B17: P8 | C17: 書式・文字装飾 | D17: 湾岸タワー店の店舗面積と客席数を答えてください。 | E17: 82m²（約25坪）、48席（うちテラス8席） | F17: 正解の要素がすべて含まれる=OK／一部のみ=部分／誤り・スライドにない内容を断定=NG | G17: 【上付き文字・2段組】P8 上付き文字（m²）、2段組テキスト | H17: OK | I17: 82m²（約25坪）、48席（うちテラス8席） | K17: 湾岸タワー店の店舗面積は82m²（約25坪）、客席数は48席（うちテラス8席）です。（スライド8「湾岸タワー店の店舗計画」より。スライド4の現地写真の看板「テナント募集 1F 82㎡」とも一致します。） | L17: 06-15
A18: 16 | B18: P8 | C18: 書式・文字装飾 | D18: 店舗計画のうち、蛍光マーカーで強調されている条件は何ですか？ | E18: 家賃は売上の10%以内 | F18: 正解の要素がすべて含まれる=OK／一部のみ=部分／誤り・スライドにない内容を断定=NG | G18: 【蛍光マーカー】P8 ハイライト（蛍光ペン）書式 | H18: OK | I18: 家賃は売上の10%以内 | K18: 蛍光マーカー（黄色の蛍光ペン）で強調されている条件は、湾岸タワー店の店舗計画（スライド8）の出店条件「家賃は売上の10%以内」です（太字でも強調されています）。 | L18: 06-16
A19: 17 | B19: P9 | C19: スライド上に見えない情報 | D19: 『商圏データの詳細』のリンク先URLを答えてください。 | E19: https://data.morino-cafe.example/area2027 | F19: 正解の要素がすべて含まれる=OK／一部のみ=部分／誤り・スライドにない内容を断定=NG | G19: 【ハイパーリンク】P9 テキストのハイパーリンク（URLは本文に表示されない） | H19: OK | I19: https://data.morino-cafe.example/area2027 | K19: 『商圏データの詳細』のリンク先URLは https://data.morino-cafe.example/area2027 です（スライド9「参考資料」の外部資料リンク）。 | L19: 06-17
A20: 18 | B20: P9 | C20: スライド上に見えない情報 | D20: 『収支の詳細はこちら』ボタンをクリックすると、どのスライドへ移動しますか？ | E20: 6枚目（収支シミュレーション） | F20: 正解の要素がすべて含まれる=OK／一部のみ=部分／誤り・スライドにない内容を断定=NG | G20: 【スライド内リンク】P9 図形のクリック時の動作（スライドへのリンク） | H20: OK | I20: スライド6「収支シミュレーション」 | K20: スライド6「収支シミュレーション」へ移動します（スライド9の「収支の詳細はこちら」ボタンはスライド内リンクで、クリックすると該当スライドへ移動します）。 | L20: 06-18
A21: 19 | B21: P10 | C21: スライド上に見えない情報 | D21: 中央駅前への出店を見送るのはどのような場合ですか？ | E21: 月額賃料が85万円を超える場合（その場合は北大学前を再検討） | F21: 正解の要素がすべて含まれる=OK／一部のみ=部分／誤り・スライドにない内容を断定=NG | G21: 【ノート】P10 ノート | H21: OK | I21: 月額賃料が85万円超なら見送り、北大学前を再検討 | K21: 中央駅前は現在賃料交渉中で、月額賃料が85万円を超える場合は出店を見送ります。その場合は、次点の北大学前を再検討します。（スライド10の発表者ノート「取扱注意」より） | L21: 06-19
A22: 20 | B22: — | C22: 記載なし | D22: 湾岸タワーの区画の月額賃料はいくらですか？ | E22: 記載なし | F22: 『記載なし』『資料からは分からない』=OK／推測と明示して答える=部分／値を断定=NG | G22: 【記載なし】全体（湾岸タワーの賃料の記載はない） | H22: OK | I22: 記載なし | J22: 家賃上限（月約73万円）を条件からの計算値と明示して補足。賃料の断定はなし | K22: 資料には、湾岸タワーの区画の月額賃料は記載されていません。 関連する記載は次のとおりです。 - スライド8の出店条件として「家賃は売上の10%以内」とされています。湾岸タワー店の年間売上目標は88百万円（8,800万円）なので、この条件から考えると家賃の上限は年880万円（月あたり約73万円）になります。ただし、これは条件から計算した上限であり、実際の賃料ではありません。 - 月額賃料の数字が出てくるのは中央駅前だけです（スライド10の発表者ノート：「月額賃料が85万円を超える場合は出店を見送り」）。湾岸タワーの数字ではありません。 - スライド4の現地写真の看板には「テナント募集 1F 82㎡」とあるだけで、賃料は書かれていません。 | L22: 06-20
A24: 記入例（行1の場合）
H25: OK | I25: （LLMの回答の要点を記入）

Sheet 07_品質改善報告
A1: 対象：07_品質改善報告_8D.pptx（10枚）
A2: No. | B2: 出題スライド | C2: 問題種別 | D2: 質問（コピペ用） | E2: 正解 | F2: 判定基準 | G2: 根拠（採点用） | H2: 判定 | I2: LLMの回答 | J2: 備考 | K2: LLMの回答（生値） | L2: テストID
A3: 1 | B3: P2 | C3: テキスト | D3: 10月の塗装ムラの発生率と、その目標値を答えてください。 | E3: 発生率3.8%、目標1.0%以下 | F3: 正解の要素がすべて含まれる=OK／一部のみ=部分／誤り・スライドにない内容を断定=NG | G3: 【テキスト】P2 | H3: OK | I3: 発生率3.8%、目標1.0%以下 | K3: 10月の塗装ムラの発生率は3.8%で、目標値は1.0%以下です（第2工場Cライン、冷蔵庫用外装パネル、10月1日〜31日）。 | L3: 07-01
A4: 2 | B4: P2 | C4: 画像 | D4: 写真の圧力計は何MPaを示していますか？ | E4: 約0.42MPa（0.40〜0.45の範囲。0.4の目盛のすぐ右） | F4: 許容範囲内の値=OK／目盛の読み違い（隣の目盛）=部分／それ以外=NG | G4: 【画像（計器の読み取り）】P2 アナログメーター画像の針の位置 | H4: OK | I4: 約0.4MPa（点検記録の実測0.42MPaも併記） | J4: 0.40は許容範囲0.40〜0.45内のためOK | K4: 写真（スライド2、11月12日撮影の塗装ブースの吐出圧力計）の針は約0.4MPaを指しています（目盛0.0〜1.0MPa、緑色の管理範囲帯 約0.3〜0.5MPaの内側）。 なお、この数値は写真の目盛からの読み取りです。同日（11/12）の設備点検記録（スライド6）では、吐出圧の実測値は0.42MPa（基準 0.40±0.05MPa、判定○）と記録されています。 | L4: 07-02
A5: 3 | B5: P3 | C5: グラフ | D5: 『異物付着』の不具合件数は何件ですか？ | E5: 27件 | F5: 正解の要素がすべて含まれる=OK／一部のみ=部分／誤り・スライドにない内容を断定=NG | G5: 【複合グラフ】P3 棒グラフ（数値ラベルなし） | H5: OK | I5: 27件（10月）。対策後は4件と補足 | K5: 『異物付着』の不具合件数は、10月（対策前）で27件です（スライド3のパレート図。10月の不具合品100件中、累積比率75%）。 なお、対策後の効果確認期間（11月13日〜17日）では4件です（スライド9。対策後の不良10件のうち）。異物付着は対策の対象外で、次の改善テーマとされています。 | L5: 07-03
A6: 4 | B6: P3 | C6: グラフ | D6: 上位2項目の累積比率は何％ですか？ | E6: 75% | F6: 正解の要素がすべて含まれる=OK／一部のみ=部分／誤り・スライドにない内容を断定=NG | G6: 【複合グラフ（第2軸）】P3 第2軸（右軸）の折れ線 | H6: OK | I6: 75% | K6: 上位2項目（膜厚不足48件・異物付着27件）の累積比率は **75%** です（10月の不具合品100件中75件で、全体の4分の3）。 | L6: 07-04
A7: 5 | B7: P3 | C7: 計算 | D7: 『タレ』と『色ムラ』の件数の合計は全体の何％ですか？ | E7: 21%（14＋7＝21件／100件） | F7: 数値が一致（丸め誤差±0.1まで）=OK／考え方は正しいが数値違い=部分／誤り=NG | G7: 【計算】P3 棒グラフ | H7: OK | I7: 21%（14＋7＝21／100） | K7: 21％です。 スライド3（10月の不具合内訳）によると、『タレ』は14件、『色ムラ』は7件で、合計21件です。不具合の総数は100件なので、21 ÷ 100 = 21％になります。 （参考：累積比率で見ても、タレまでの89％から異物付着までの75％を引くと14％、色ムラまでの96％からタレまでの89％を引くと7％で、足すと21％です。） ※対策後（11月13日〜17日、スライド9）の内訳には『色ムラ』の項目がありません。その期間で数えると、タレ2件のみで10件中20％になります。 | L7: 07-05
A8: 6 | B8: P4 | C8: 図解・位置関係 | D8: 特性要因図で『材料』に分類されている要因は何ですか？ | E8: 塗料粘度のばらつき | F8: 正解の要素がすべて含まれる=OK／一部のみ=部分／誤り・スライドにない内容を断定=NG | G8: 【図解（特性要因図）】P4 骨の位置と分類ラベル | H8: OK | I8: 塗料粘度のばらつき | K8: 特性要因図（スライド4、特性＝膜厚不足）で「材料」に分類されている要因は「塗料粘度のばらつき」です（材料の枝にはこの1項目のみ）。 | L8: 07-06
A9: 7 | B9: P4 | C9: 図解・位置関係 | D9: 真因として赤丸で囲まれている要因と、その分類を答えてください。 | E9: スプレーガンのノズル摩耗（機械） | F9: 正解の要素がすべて含まれる=OK／一部のみ=部分／誤り・スライドにない内容を断定=NG | G9: 【図形による強調】P4 楕円の囲み＋注記 | H9: OK | I9: スプレーガンのノズル摩耗（機械） | K9: 真因として赤丸で囲まれている要因は「スプレーガンのノズル摩耗」で、分類は4M（人・機械・材料・方法）のうち「機械」です（スライド4の特性要因図）。図中で赤丸が付いているのはこの要因のみです。 | L9: 07-07
A10: 8 | B10: P5 | C10: グラフ | D10: 膜厚が管理限界を外れた日と、その値を答えてください。 | E10: 9日、43μm（下方管理限界44μmを下回った） | F10: 正解の要素がすべて含まれる=OK／一部のみ=部分／誤り・スライドにない内容を断定=NG | G10: 【管理図】P5 折れ線（数値ラベルなし） | H10: OK | I10: 11月9日、43μm（LCL44μm割れ） | K10: 膜厚が管理限界を外れたのは **11月9日** で、その値は **43μm** です（下方管理限界 LCL 44μm を下回りました）。 | L10: 07-08
A11: 9 | B11: P5 | C11: グラフ | D11: 上方管理限界と下方管理限界の値をそれぞれ答えてください。 | E11: UCL 56μm、LCL 44μm | F11: 正解の要素がすべて含まれる=OK／一部のみ=部分／誤り・スライドにない内容を断定=NG | G11: 【管理図】P5 グラフの系列データ | H11: OK | I11: UCL 56μm、LCL 44μm | K11: スライド5「膜厚の管理図（11月1日〜12日）」によると、 - 上方管理限界（UCL）：56μm - 下方管理限界（LCL）：44μm （中心線CLは50μm。管理限界は過去3か月のデータから算出されています。） | L11: 07-09
A12: 10 | B12: P6 | C12: 画像 | D12: 点検記録表で判定が『×』になっている項目をすべて答えてください。 | E12: ノズル径、塗料粘度 | F12: 正解の要素がすべて含まれる=OK／一部のみ=部分／誤り・スライドにない内容を断定=NG | G12: 【画像（スキャン文書）】P6 傾いたスキャン画像 | H12: OK | I12: ノズル径、塗料粘度 | K12: 点検記録表（11/12、第2工場 Cライン）で判定が「×」になっている項目は次の2つです。 1. ノズル径（基準 1.30±0.05mm に対し実測 1.52mm） 2. 塗料粘度（基準 18±2秒 に対し実測 21秒） | L12: 07-10
A13: 11 | B13: P6 | C13: 画像 | D13: ノズル径の実測値と基準値を答えてください。 | E13: 実測1.52mm、基準1.30±0.05mm | F13: 正解の要素がすべて含まれる=OK／一部のみ=部分／誤り・スライドにない内容を断定=NG | G13: 【画像（手書き）】P6 スキャン画像（実測は手書き） | H13: OK | I13: 実測1.52mm、基準1.30±0.05mm | K13: ノズル径の実測値は1.52mm、基準値は1.30±0.05mmです（スライド6の設備点検記録、11/12点検。判定は×＝基準外）。 | L13: 07-11
A14: 12 | B14: P6 | C14: 画像 | D14: 点検記録表の点検日と点検者を答えてください。 | E14: 11月12日、山岸 | F14: 正解の要素がすべて含まれる=OK／一部のみ=部分／誤り・スライドにない内容を断定=NG | G14: 【画像（手書き）】P6 スキャン画像（手書き） | H14: OK | I14: 11/12、山岸 | K14: 点検記録表（スライド6、塗装設備 点検記録表／第2工場 Cライン）によると、 - 点検日：11/12（手書き） - 点検者：山岸（手書き） です。 | L14: 07-12
A15: 13 | B15: P7 | C15: 書式・文字装飾 | D15: 対策前と対策後の工程能力指数（Cpk）を答えてください。目標は達成していますか？ | E15: 0.71→1.45。目標1.33以上を達成 | F15: 正解の要素がすべて含まれる=OK／一部のみ=部分／誤り・スライドにない内容を断定=NG | G15: 【下付き文字】P7 下付き文字（pk） | H15: OK | I15: 0.71→1.45、目標1.33以上を達成 | K15: 工程能力指数（Cpk）は、対策前が0.71、対策後が1.45です（スライド7「対策と効果」より）。 工程能力の目標は「1.33以上」とされているため、対策後のCpk 1.45は目標を達成しています（対策前の0.71は目標未達でした）。 | L15: 07-13
A16: 14 | B16: P7 | C16: 計算 | D16: 膜厚のばらつき（σ）は何％低減しましたか？小数第1位まで答えてください。 | E16: 60.4%（(4.8−1.9)÷4.8） | F16: 数値が一致（丸め誤差±0.1まで）=OK／考え方は正しいが数値違い=部分／誤り=NG | G16: 【計算】P7 | H16: OK | I16: 約60.4% | K16: 膜厚のばらつき（σ）は 4.8μm → 1.9μm に低減しています（スライド7）。 低減率 =（4.8 − 1.9）÷ 4.8 = 2.9 ÷ 4.8 ≒ 0.6042 答え：約 60.4％ 低減 | L16: 07-14
... A22: 20 | B22: P10 | C22: スライド上に見えない情報 | D22: 第1工場Bラインの粘度自動測定はいつ実施する予定ですか？ | E22: 2027年2月（設備更新に合わせて） | F22: 正解の要素がすべて含まれる=OK／一部のみ=部分／誤り・スライドにない内容を断定=NG | G22: 【ノート】P10 ノート | H22: OK | I22: 2027年2月（設備更新に合わせて） | K22: 2027年2月の予定です。設備更新に合わせて実施する計画となっています（現時点では未着手）。 | L22: 07-20
A24: 記入例（行1の場合）
H25: OK | I25: （LLMの回答の要点を記入）

Sheet 08_デジタル広告
A1: 対象：08_デジタル広告_効果検証.pptx（10枚）
A2: No. | B2: 出題スライド | C2: 問題種別 | D2: 質問（コピペ用） | E2: 正解 | F2: 判定基準 | G2: 根拠（採点用） | H2: 判定 | I2: LLMの回答 | J2: 備考 | K2: LLMの回答（生値） | L2: テストID
A3: 1 | B3: 全体 | C3: 画像 | D3: この資料に掲載されている数値は確定値ですか？ | E3: 確定値ではない（速報値・確定前） | F3: 正解の要素がすべて含まれる=OK／一部のみ=部分／誤り・スライドにない内容を断定=NG | G3: 【背景画像】P2〜P10 スライド背景画像の透かし文字 | H3: OK | I3: 確定値ではない（速報値・確定前の透かし） | K3: いいえ、確定値ではありません。 スライド2〜10には「速報値（確定前）」の透かしが入っており、本資料の数値はすべて確定前の速報値として扱う必要があります。 補足として、スライド9の日別データの合計（表示1,128,224回／クリック33,829回／購入1,017件、10/12欠測日を除く30日分）は、スライド2のファネルの数値（表示1,250,000回／クリック37,500回／購入1,080件）を下回っています。この差は欠測日1日分だけでは説明しにくいため、集計範囲や確定値との違いを確認する必要があるとされています。 | L3: 08-01
A4: 2 | B4: P2 | C4: 図解・位置関係 | D4: 広告のクリック率（CTR）は何％ですか？ | E4: 3.0% | F4: 正解の要素がすべて含まれる=OK／一部のみ=部分／誤り・スライドにない内容を断定=NG | G4: 【図解（フリーフォーム）】P2 ファネル横の数値 | H4: OK | I4: 3.0% | K4: 広告のクリック率（CTR）は、全体で3.0%です（広告表示1,250,000回に対しクリック37,500回。スライド2のファネルより）。 なお、本資料の数値はすべて確定前の速報値です。 参考： - バナー別では、バナーA（機能訴求）が3.4%、バナーB（情緒・季節訴求）が2.6%です（スライド7）。 - スライド9の日別データ（10/12欠測を除く30日分）から計算すると、33,829÷1,128,224≒3.0%で、ほぼ同じ値になります。 | L4: 08-02
A5: 3 | B5: P2 | C5: 計算 | D5: カート投入から購入に至った割合は何％ですか？ | E5: 30%（1,080÷3,600） | F5: 数値が一致（丸め誤差±0.1まで）=OK／考え方は正しいが数値違い=部分／誤り=NG | G5: 【計算】P2 ファネル | H5: OK | I5: 30.0%（1,080÷3,600） | K5: カート投入から購入に至った割合は30.0％です（カート投入3,600件→購入1,080件）。 | L5: 08-03
A6: 4 | B6: P2 | C6: 図解・位置関係 | D6: 商品ページの閲覧数はいくつですか？ | E6: 22,500回 | F6: 正解の要素がすべて含まれる=OK／一部のみ=部分／誤り・スライドにない内容を断定=NG | G6: 【図解（フリーフォーム）】P2 ファネル（台形の図形に重ねた文字） | H6: OK | I6: 22,500回 | K6: 商品ページの閲覧数は22,500回です（スライド2「購入までのファネル」より）。クリック37,500回からの遷移率は60.0%です。なお、本資料の数値は確定前の速報値です。 | L6: 08-04
A7: 5 | B7: P3 | C7: グラフ | D7: CPAが最も高いチャネルと、その値を答えてください。 | E7: 動画、6,500円 | F7: 正解の要素がすべて含まれる=OK／一部のみ=部分／誤り・スライドにない内容を断定=NG | G7: 【複合グラフ（第2軸）】P3 第2軸の折れ線（数値ラベルなし） | H7: OK | I7: 動画、6,500円 | K7: CPAが最も高いチャネルは**動画広告**で、CPAは**6,500円**です（スライド3・5より。なお数値は確定前の速報値）。 | L7: 08-05
A8: 6 | B8: P3 | C8: 図解・位置関係 | D8: グラフ上の注釈は、どのチャネルについて何を説明していますか？ | E8: SNS。インフルエンサー起用（10/5〜） | F8: 正解の要素がすべて含まれる=OK／一部のみ=部分／誤り・スライドにない内容を断定=NG | G8: 【図形による注釈】P3 グラフに重ねた矢印とテキスト（位置で対応） | H8: OK | I8: SNS、インフルエンサー起用（10/5〜） | K8: グラフ上の注釈（スライド3「チャネル別の広告費とCPA」の吹き出し注記）は、SNS広告について説明しています。 - 注釈の内容：「インフルエンサー起用（10/5〜）」 - 矢印がSNSの棒（広告費）を指しており、SNS広告で10月5日からインフルエンサーを起用したことを示しています。 参考として、考察（スライド8）では、インフルエンサーの投稿後にSNS経由の流入は増えたものの購入率が低く、SNS広告のCPAが悪化したこと（実績4,100円、目標3,500円）を課題に挙げています。 なお、スライド4の週別流入グラフにも赤い破線のマーカー「キャンペーン開始」（W3の位置）があります。ただしこれは特定のチャネルについての注釈ではなく、期間の区切りを示すものです。 | L8: 08-06
A9: 7 | B9: P3 | C9: 計算 | D9: 4チャネルの広告費の合計はいくらですか？ | E9: 446.6万円（126＋123＋130＋67.6） | F9: 数値が一致（丸め誤差±0.1まで）=OK／考え方は正しいが数値違い=部分／誤り=NG | G9: 【計算】P3 棒グラフ（数値ラベルなし） | H9: OK | I9: 446.6万円 | K9: 4チャネル（検索・SNS・動画・ディスプレイ）の広告費の合計は **446.6万円**（4,466,000円）です。 内訳（2026年10月、スライド3）： - 検索：126万円 - SNS：123万円 - 動画：130万円 - ディスプレイ：67.6万円 ※資料の数値は確定前の速報値です。 | L9: 08-07
A10: 8 | B10: P4 | C10: グラフ | D10: SNS経由のセッション数が最も多かった週と、その数を答えてください。 | E10: W4、12千（12,000） | F10: 正解の要素がすべて含まれる=OK／一部のみ=部分／誤り・スライドにない内容を断定=NG | G10: 【面グラフ】P4 積み上げ面グラフ | H10: OK | I10: W4、12千セッション | K10: SNS経由のセッション数が最も多かったのは W4 で、12千セッション（約12,000セッション）です。 （スライド4「週別の流入数」より。なお資料の注記ではW1が9月第4週、10月1日を含む週がW2とされており、W4はその2週後にあたります。数値は速報値です。） | L10: 08-08
A11: 9 | B11: P4 | C11: 図解・位置関係 | D11: キャンペーンは何週目に開始しましたか？ | E11: W3（W3の位置に開始線） | F11: 正解の要素がすべて含まれる=OK／一部のみ=部分／誤り・スライドにない内容を断定=NG | G11: 【図形の位置】P4 グラフに重ねた破線の位置 | H11: OK | I11: グラフ上はW3、期間（10/1開始）に基づけばW2。要確認 | J11: 正解W3を含み、誤りの断定なし（W2は資料の要確認注記に基づく併記） | K11: 資料上の記載は一致していません。 - スライド4のグラフでは、「キャンペーン開始」を示す赤の破線マーカーが **W3** の位置に引かれています。 - 一方、注記では「W1は9月第4週（10月1日を含む週をW2とする）」とされており、キャンペーン期間（2026年10月1日開始）に従えば開始週は **W2** になります。 資料自体にも「※要確認」として、開始線がW3に引かれているのはインフルエンサー起用開始（10/5〜）の週に相当する可能性がある、と注記されています（週の起算曜日は資料に記載なし）。 まとめると、グラフの表示上はW3、キャンペーン期間（10月1日開始）に基づけばW2です。どちらが正しいかは作成部署への確認が必要です。 | L11: 08-09
A12: 10 | B12: P5 | C12: 表 | D12: KPIの判定で目標を達成したチャネルはどれですか？ | E12: 検索のみ | F12: 正解の要素がすべて含まれる=OK／一部のみ=部分／誤り・スライドにない内容を断定=NG | G12: 【結合セル】P5 2段見出しの表 | H12: OK | I12: 検索のみ | K12: KPIの判定で目標を達成した（判定「○」）のは検索広告のみです。 - 検索：目標CPA 3,000円以下 → 実績2,800円、目標購入数400件以上 → 実績450件 → ○ 判定基準は「CPAが目標以下、かつ購入数が目標以上」で、他のチャネルは×です。 - SNS：CPA 4,100円（目標3,500円）、購入300件（目標350件）→ どちらも未達 - 動画：CPA 6,500円（目標5,000円）、購入200件（目標250件）→ どちらも未達 - ディスプレイ：購入130件は目標120件を上回ったものの、CPA 5,200円が目標5,000円を超えたため× なお、全体の購入数1,080件は目標1,120件に届いていません（数値はすべて確定前の速報値です）。 | L12: 08-10
A13: 11 | B13: P5 | C13: 計算 | D13: 全体の購入数は、目標に対して何％達成しましたか？小数第1位まで答えてください。 | E13: 96.4%（1,080÷1,120） | F13: 数値が一致（丸め誤差±0.1まで）=OK／考え方は正しいが数値違い=部分／誤り=NG | G13: 【計算】P5 表 | H13: OK | I13: 約96.4% | K13: 全体の購入数は実績1,080件、目標1,120件で、達成率は約96.4％です（1,080÷1,120＝0.9643）。目標には届いていません。 ※資料の数値は確定前の速報値です。 | L13: 08-11
A14: 12 | B14: P6 | C14: グラフ | D14: リピート率が最も高い年代と、その値を答えてください。 | E14: 50代以上、41% | F14: 正解の要素がすべて含まれる=OK／一部のみ=部分／誤り・スライドにない内容を断定=NG | G14: 【散布図】P6 散布図（数値ラベルなし） | H14: OK | I14: 50代以上、41% | K14: リピート率が最も高い年代は「50代以上」で、その値は41%です（スライド6「年代別の購入傾向」の散布図データより）。 | L14: 08-12
A15: 13 | B15: P6 | C15: グラフ | D15: 平均購入単価が5,000円未満の年代はどれですか？ | E15: 20代（3,800円） | F15: 正解の要素がすべて含まれる=OK／一部のみ=部分／誤り・スライドにない内容を断定=NG | G15: 【散布図】P6 散布図 | H15: OK | I15: 20代（3,800円） | K15: 平均購入単価が5,000円未満の年代は「20代」です（平均購入単価3,800円）。 ※30代は5,200円、40代は6,900円、50代以上は7,400円で、いずれも5,000円以上です（スライド6「年代別の購入傾向」、数値は速報値）。 | L15: 08-13
A16: 14 | B16: P6 | C16: 書式・文字装飾 | D16: 縦書きで掲載されている『顧客の声』の内容を答えてください。 | E16: 「香りが長続きして気に入っています」（五十代・女性） | F16: 正解の要素がすべて含まれる=OK／一部のみ=部分／誤り・スライドにない内容を断定=NG | G16: 【縦書き】P6 縦書きテキストボックス | H16: OK | I16: 「香りが長続きして気に入っています」（五十代・女性） | K16: スライド6「年代別の購入傾向」に、縦書きの囲み枠で次の顧客の声が載っています。 「香りが長続きして気に入っています」（五十代・女性） 補足：資料の注記にあるとおり、声の主の属性は漢数字で「五十代」と書かれています。グラフの区分は「50代以上」なので、表記がそろっていません。 | L16: 08-14
A17: 15 | B17: P7 | C17: 画像 | D17: クリック率が高かったバナーのキャッチコピーを答えてください。 | E17: 「うるおい、72時間。」（バナーA、CTR 3.4%） | F17: 正解の要素がすべて含まれる=OK／一部のみ=部分／誤り・スライドにない内容を断定=NG | G17: 【画像内文字】P7 バナー画像＋表 | H17: OK | I17: 「うるおい、72時間。」（バナーA、CTR3.4%） | K17: クリック率が高かったのはバナーA（CTR 3.4%、バナーBは2.6%）で、そのキャッチコピーは「うるおい、72時間。」です（商品：LUMIERE モイストセラム、機能訴求）。 | L17: 08-15
A18: 16 | B18: P8 | C18: 書式・文字装飾 | D18: 『課題』の下に挙げられている項目をすべて答えてください。 | E18: SNS広告のCPA悪化、動画広告の費用対効果（＋それぞれの補足） | F18: 正解の要素がすべて含まれる=OK／一部のみ=部分／誤り・スライドにない内容を断定=NG | G18: 【階層構造・2段組】P8 箇条書きのインデント階層 | H18: OK | I18: SNS広告のCPA悪化、動画広告の費用対効果（＋補足） | K18: 『課題』（スライド8：考察）の下に挙げられている項目は以下の2つです。 1. SNS広告のCPA悪化 - インフルエンサー投稿後に流入は増えたが、購入率が低い 2. 動画広告の費用対効果 - 視聴完了率 22%（目標 35%） | L18: 08-16
A19: 17 | B19: P8 | C19: 書式・文字装飾 | D19: 動画広告の視聴完了率と、その目標値を答えてください。 | E19: 22%（目標35%） | F19: 正解の要素がすべて含まれる=OK／一部のみ=部分／誤り・スライドにない内容を断定=NG | G19: 【階層構造】P8 第3階層の箇条書き | H19: OK | I19: 22%（目標35%） | K19: 動画広告の視聴完了率は22%で、目標値は35%です（スライド8「考察」の課題欄より。目標に対して13ポイント未達）。なお、本資料の数値はすべて確定前の速報値です。 | L19: 08-17
A20: 18 | B20: P9 | C20: スライド上に見えない情報 | D20: 日別データの中で、欠測となっている日はいつですか？理由も答えてください。 | E20: 2026年10月12日。計測タグの不具合 | F20: 正解の要素がすべて含まれる=OK／一部のみ=部分／誤り・スライドにない内容を断定=NG | G20: 【埋め込みExcel】P9 埋め込みExcelファイル内のデータと注記 | H20: OK | I20: 2026年10月12日、計測タグの不具合 | K20: 欠測となっている日は **2026年10月12日** です（表示回数・クリック・購入のすべてが欠測）。 理由：**計測タグの不具合**によるものです（スライド9の埋め込みExcel「日別」シート内の注記「※10/12は計測タグの不具合により欠測」）。 | L20: 08-18
A21: 19 | B21: P10 | C21: スライド上に見えない情報 | D21: 動画広告は今後どうする方向ですか？ | E21: 12月の配信結果が改善しなければ2027年1月で停止する方向（社内合意前） | F21: 正解の要素がすべて含まれる=OK／一部のみ=部分／誤り・スライドにない内容を断定=NG | G21: 【ノート】P10 ノート | H21: OK | I21: 配信内容見直し・予算80万円に減額。ノートより「12月改善なければ2027年1月で停止の方向（社内合意前）」 | K21: 資料（スライド10「次期施策と予算配分（案）」）によると、動画広告は「配信内容を見直す」方向です。 - 予算：10月の130万円から、次期（12月）は80万円に減らす案です（−50万円）。全チャネルで最も大きい減額です。 - 理由（スライド3・5・8）：CPAが6,500円で全チャネル中もっとも高く、目標の5,000円を超えています。購入数も200件で、目標の250件に届いていません。視聴完了率も22%で、目標の35%を下回っており、「費用対効果」が課題に挙げられています。 なお、スライド10の発表者ノートには「12月の配信結果が改善しなければ2027年1月で停止する方向」と書かれています。ただしこれは社内合意前の情報で、資料本体には載せない扱いになっているため、取扱いには注意が必要です。 | L21: 08-19
A22: 20 | B22: — | C22: 記載なし | D22: 年代別の購入者数を答えてください。 | E22: 記載なし | F22: 『記載なし』『資料からは分からない』=OK／推測と明示して答える=部分／値を断定=NG | G22: 【記載なし】P6（単価とリピート率のみ） | H22: OK | I22: 記載なし（単価とリピート率のみ） | K22: 資料には、年代別の購入者数（人数・件数）は記載されていません。 スライド6「年代別の購入傾向」に載っているのは、年代別の平均購入単価とリピート率だけです。 | 年代 | 平均購入単価（円） | リピート率（%） | | --- | --- | --- | | 20代 | 3,800 | 18 | | 30代 | 5,200 | 26 | | 40代 | 6,900 | 34 | | 50代以上 | 7,400 | 41 | 全体の購入数は1,080件（スライド2・5、速報値）ですが、年代ごとの内訳はありません。年代別の購入者数を知りたい場合は、元データを作成部署（デジタルマーケティング部）に確認する必要があります。 | L22: 08-20
A24: 記入例（行1の場合）
H25: OK | I25: （LLMの回答の要点を記入）

Sheet 09_組織再編案
A1: 対象：09_組織再編案.pptx（10枚）
A2: No. | B2: 出題スライド | C2: 問題種別 | D2: 質問（コピペ用） | E2: 正解 | F2: 判定基準 | G2: 根拠（採点用） | H2: 判定 | I2: LLMの回答 | J2: 備考 | K2: LLMの回答（生値） | L2: テストID
A3: 1 | B3: 全体 | C3: スライド上に見えない情報 | D3: この資料のバージョンと改訂日を答えてください。 | E3: Ver.3.2、2026年11月2日改訂 | F3: 正解の要素がすべて含まれる=OK／一部のみ=部分／誤り・スライドにない内容を断定=NG | G3: 【スライドレイアウト】スライドレイアウト（マスター側）に配置したテキスト。各スライドには含まれない | H3: OK | I3: Ver.3.2、2026年11月2日改訂 | K3: この資料のバージョンは「Ver.3.2」、改訂日は「2026/11/02」（2026年11月2日）です。 ※全スライドの右上に「Ver.3.2（2026/11/02 改訂）」と表示されています。なお、資料内の注記では、発表者ノートに11月25日に実施済みの事項（労働組合への説明）が書かれているため、ノートと本文で更新した時期が異なる可能性があると指摘されています。 | L3: 09-01
A4: 2 | B4: 全体 | C4: スライド上に見えない情報 | D4: 資料の『第2部』のセクション名と、含まれるスライドの範囲を答えてください。 | E4: 第2部 新組織案（スライド5〜8） | F4: 正解の要素がすべて含まれる=OK／一部のみ=部分／誤り・スライドにない内容を断定=NG | G4: 【セクション】プレゼンテーションのセクション設定 | H4: NG | I4: 「第2部」のセクション記載なし、回答不可 | J4: NG：入力MDにセクション情報（第2部 新組織案／スライド5〜8）がなく、資料から正解を答えられないためNG | K4: 資料には「第2部」というセクション（部構成）の記載がありません。 この資料はスライド1〜10が「スライド1：表紙」「スライド2：部門間の業務重複」…「スライド10：決裁事項とスケジュール」と順番に並んでいるだけで、「第1部」「第2部」といった部の区分やセクション名は書かれていません。そのため、「第2部」のセクション名とスライドの範囲は資料からは答えられません。 | L4: 09-02
A5: 3 | B5: P2 | C5: 図解・位置関係 | D5: 3部門すべてで重複している業務は何件ですか？ | E5: 5件 | F5: 正解の要素がすべて含まれる=OK／一部のみ=部分／誤り・スライドにない内容を断定=NG | G5: 【図解（ベン図）】P2 円の重なりの中央 | H5: OK | I5: 5件 | K5: 3部門すべてで重複している業務は5件です（スライド2のベン図より）。 | L5: 09-03
A6: 4 | B6: P2 | C6: 図解・位置関係 | D6: 営業部とCS部の2部門だけで重複している業務は何件ですか？ | E6: 9件 | F6: 正解の要素がすべて含まれる=OK／一部のみ=部分／誤り・スライドにない内容を断定=NG | G6: 【図解（ベン図）】P2 ベン図の位置 | H6: OK | I6: 9件 | K6: 営業部とCS部の2部門だけで重複している業務は9件です（スライド2のベン図「営業部 ∩ CS部（2部門重複）」）。3部門すべてで重複している5件は含みません。 | L6: 09-04
A7: 5 | B7: P2 | C7: 計算 | D7: 営業部が他部門と重複して行っている業務は合計何件ですか？ | E7: 26件（12＋9＋5） | F7: 数値が一致（丸め誤差±0.1まで）=OK／考え方は正しいが数値違い=部分／誤り=NG | G7: 【計算】P2 ベン図 | H7: OK | I7: 26件（12＋9＋5） | K7: 営業部が他部門と重複して行っている業務は合計 **26件** です。 内訳（スライド2のベン図より）： - 営業部 ∩ マーケティング部（2部門重複）：12件 - 営業部 ∩ CS部（2部門重複）：9件 - 3部門すべてで重複：5件 12 + 9 + 5 = 26件（営業部の関与件数44件から営業部のみの18件を引いた数とも一致します）。 | L7: 09-05
A8: 6 | B8: P3 | C8: 図解・位置関係 | D8: 『顧客情報が分散』のグループに属する付箋の内容をすべて答えてください。 | E8: 顧客リストが部署ごとに別／問い合わせ履歴が共有されない／同じ顧客に重複して連絡／Excel管理が限界 | F8: 正解の要素がすべて含まれる=OK／一部のみ=部分／誤り・スライドにない内容を断定=NG | G8: 【位置（親和図）】P3 付箋の配置（グループ化なし・回転あり） | H8: OK | I8: 顧客リストが部署ごとに別／問い合わせ履歴が共有されない／同じ顧客に重複して連絡／Excel管理が限界 | K8: 『顧客情報が分散』のグループに属する付箋は次の4枚です（スライド3：現場の声の親和図より）。 - 顧客リストが部署ごとに別 - 問い合わせ履歴が共有されない - 同じ顧客に重複して連絡 - Excel管理が限界 | L8: 09-06
A9: 7 | B9: P3 | C9: 図解・位置関係 | D9: 付箋の枚数が最も少ないグループと、その枚数を答えてください。 | E9: 評価が不透明、2枚 | F9: 正解の要素がすべて含まれる=OK／一部のみ=部分／誤り・スライドにない内容を断定=NG | G9: 【位置（親和図）】P3 付箋の配置 | H9: OK | I9: 評価が不透明、2枚 | K9: 付箋の枚数が最も少ないグループは「評価が不透明」で、付箋は2枚です（「評価基準が部署で違う」「成果が見えにくい」）。 参考：「意思決定が遅い」は3枚、「顧客情報が分散」は4枚です。 | L9: 09-07
A10: 8 | B10: P4 | C10: 画像 | D10: DX成熟度の評価が最も低い部門と、その評価を答えてください。 | E10: CS部、★1つ（5段階中1） | F10: 正解の要素がすべて含まれる=OK／一部のみ=部分／誤り・スライドにない内容を断定=NG | G10: 【画像（アイコン）】P4 表のセルに重ねた星の画像 | H10: OK | I10: CS部、★1つ（1/5） | K10: DX成熟度の評価が最も低い部門はCS部で、評価は★1つ（1/5、★☆☆☆☆）です（2026年9月 社内アセスメント、★5段階）。 | L10: 09-08
A11: 9 | B11: P4 | C11: 画像 | D11: DX成熟度が星4つの部門はどこですか？ | E11: マーケティング部 | F11: 正解の要素がすべて含まれる=OK／一部のみ=部分／誤り・スライドにない内容を断定=NG | G11: 【画像（アイコン）】P4 星の画像の数 | H11: OK | I11: マーケティング部 | K11: DX成熟度が星4つ（★★★★☆、4/5）の部門は「マーケティング部」です（スライド4、2026年9月 社内アセスメント）。 | L11: 09-09
A12: 10 | B12: P5 | C12: 図解・位置関係 | D12: 新組織図で、兼務の関係にあるのはどの組織とどの組織ですか？ | E12: データ戦略室とマーケティング部（データ戦略室の小野室長がマーケティング部長を兼ねる） | F12: 正解の要素がすべて含まれる=OK／一部のみ=部分／誤り・スライドにない内容を断定=NG | G12: 【図解（線種）】P5 破線のコネクタ＋凡例 | H12: OK | I12: データ戦略室とマーケティング部（小野室長が部長を兼務） | K12: 新組織図（スライド5）で兼務の関係にあるのは、「データ戦略室」と「マーケティング部」です。 図ではこの2つの組織がオレンジの破線で結ばれています。凡例によると、破線は「兼務（室長が部長を兼ねる）」を表します。つまり、データ戦略室長の小野氏がマーケティング部長を兼ねています。 なお、この兼務はスライド本文に文章で書かれているわけではありません。図の線の位置から読み取ったものです。 | L12: 09-10
A13: 11 | B13: P5 | C13: 図解・位置関係 | D13: データ戦略室はどの本部の下に置かれますか？本部長は誰ですか？ | E13: 技術本部（本部長 三浦） | F13: 正解の要素がすべて含まれる=OK／一部のみ=部分／誤り・スライドにない内容を断定=NG | G13: 【図解（組織図）】P5 コネクタ | H13: OK | I13: 技術本部、本部長 三浦 | K13: データ戦略室は技術本部の下に置かれます。技術本部の本部長は三浦です。（なお、データ戦略室の室長は小野です。） | L13: 09-11
A14: 12 | B14: P6 | C14: 表 | D14: データ戦略室がA（説明責任）を持つ業務は何ですか？ | E14: 顧客データ基盤の運用 | F14: 正解の要素がすべて含まれる=OK／一部のみ=部分／誤り・スライドにない内容を断定=NG | G14: 【表（RACI）】P6 RACI表 | H14: OK | I14: 顧客データ基盤の運用 | K14: データ戦略室がA（説明責任）を持つ業務は「顧客データ基盤の運用」（データ区分）の1件です。 （スライド6のRACI表より。なお同じデータ区分の「KPIレポーティング」は、データ戦略室はR（実行責任）で、A（説明責任）は経営企画部となっています。キーメッセージ「データ関連業務の説明責任をデータ戦略室に集約する」とは食い違いがあり、資料上も要確認とされています。） | L14: 09-12
A15: 13 | B15: P6 | C15: 表 | D15: 『予算策定』の実行責任（R）を持つのはどこですか？ | E15: 経営企画部（A/R） | F15: 正解の要素がすべて含まれる=OK／一部のみ=部分／誤り・スライドにない内容を断定=NG | G15: 【表（RACI）】P6 RACI表 | H15: OK | I15: 経営企画部（A/R） | K15: 『予算策定』の実行責任（R）を持つのは**経営企画部**です。 スライド6の役割分担（RACI）表で、「予算策定」の行は経営企画部が「A/R」となっており、説明責任（A）と実行責任（R）の両方を経営企画部が担っています。なお、事業本部・技術本部はC（協議先）、データ戦略室はI（報告先）です。 | L15: 09-13
A16: 14 | B16: P6 | C16: 表 | D16: 『データ』区分に含まれる業務をすべて答えてください。 | E16: 顧客データ基盤の運用、KPIレポーティング | F16: 正解の要素がすべて含まれる=OK／一部のみ=部分／誤り・スライドにない内容を断定=NG | G16: 【結合セル】P6 縦に結合されたセル | H16: OK | I16: 顧客データ基盤の運用、KPIレポーティング | K16: 『データ』区分に含まれる業務は次の2つです（スライド6：役割分担（RACI））。 1. 顧客データ基盤の運用 2. KPIレポーティング | L16: 09-14
... A22: 20 | B22: P10 | C22: スライド上に見えない情報 | D22: 労働組合への説明は済んでいますか？ | E22: 11月25日に実施済み（大きな異論なし） | F22: 正解の要素がすべて含まれる=OK／一部のみ=部分／誤り・スライドにない内容を断定=NG | G22: 【ノート】P10 ノート | H22: OK | I22: 11月25日に実施済み、大きな異論なし | K22: はい、資料上は済んでいることになっています。スライド10の発表者ノート（取扱注意）に「労働組合への説明は11月25日に実施済みで、大きな異論は出ていない」と記載されています。 ただし、以下の点にご注意ください。 - この情報はスライド本文ではなく発表者ノートにのみ記載された、労使関係に関する内部情報です。共有範囲に注意が必要とされています。 - 資料の版数は「Ver.3.2（2026/11/02 改訂）」ですが、ノートには11月25日に実施済みの事項が書かれており、ノートと本文の更新時点が異なる可能性があります。最新の状況は担当部署（経営企画部）にご確認ください。 | L22: 09-20
A24: 記入例（行1の場合）
H25: OK | I25: （LLMの回答の要点を記入）

Sheet 10_技術ロードマップ
A1: 対象：10_技術開発ロードマップ.pptx（10枚）
A2: No. | B2: 出題スライド | C2: 問題種別 | D2: 質問（コピペ用） | E2: 正解 | F2: 判定基準 | G2: 根拠（採点用） | H2: 判定 | I2: LLMの回答 | J2: 備考 | K2: LLMの回答（生値） | L2: テストID
A3: 1 | B3: P2 | C3: グラフ | D3: 第2世代のサイクル寿命は何回ですか？ | E3: 2,000回 | F3: 正解の要素がすべて含まれる=OK／一部のみ=部分／誤り・スライドにない内容を断定=NG | G3: 【対数グラフ】P2 縦軸が対数目盛の折れ線（数値ラベルなし） | H3: OK | I3: 2,000回 | K3: 第2世代のサイクル寿命は2,000回です（スライド2「世代別の充放電サイクル寿命」より）。なお、ここでのサイクル寿命は「容量が初期の80%に下がるまでに繰り返せる充放電の回数」と定義されています。 | L3: 10-01
A4: 2 | B4: P2 | C4: 計算 | D4: 最終目標のサイクル寿命は、第1世代の何倍ですか？ | E4: 100倍（50,000÷500） | F4: 数値が一致（丸め誤差±0.1まで）=OK／考え方は正しいが数値違い=部分／誤り=NG | G4: 【計算】P2 対数グラフ | H4: OK | I4: 100倍 | K4: 100倍です。最終目標のサイクル寿命は50,000回、第1世代は500回なので、50,000 ÷ 500 ＝ 100倍になります（スライド2のグラフより）。 | L4: 10-02
A5: 3 | B5: P3 | C5: グラフ | D5: エネルギー密度が2番目に高いのはどこですか？値も答えてください。 | E5: A社、350Wh/kg | F5: 正解の要素がすべて含まれる=OK／一部のみ=部分／誤り・スライドにない内容を断定=NG | G5: 【軸の逆順】P3 横棒グラフ（項目軸を逆順に設定） | H5: OK | I5: A社、350Wh/kg | K5: エネルギー密度（重量エネルギー密度）が2番目に高いのは **A社** で、値は **350 Wh/kg** です。 （1位は当社 第3世代（開発中）の420 Wh/kg。出典：スライド3、競合の値は各社の公開資料による2026年9月時点の値） | L5: 10-03
A6: 4 | B6: P3 | C6: 計算 | D6: 当社の第3世代とC社のエネルギー密度の差は何Wh/kgですか？ | E6: 140Wh/kg（420−280） | F6: 数値が一致（丸め誤差±0.1まで）=OK／考え方は正しいが数値違い=部分／誤り=NG | G6: 【計算】P3 横棒グラフ | H6: OK | I6: 140Wh/kg | K6: 当社の第3世代（420 Wh/kg）とC社（280 Wh/kg）のエネルギー密度の差は、140 Wh/kgです。 | L6: 10-04
A7: 5 | B7: P4 | C7: 書式・文字装飾 | D7: 正極材の化学式で、ニッケルの組成比はいくつですか？ | E7: 0.8（LiNi₀.₈Mn₀.₁Co₀.₁O₂） | F7: 正解の要素がすべて含まれる=OK／一部のみ=部分／誤り・スライドにない内容を断定=NG | G7: 【下付き文字（化学式）】P4 下付き文字 | H7: OK | I7: 0.8 | K7: 正極材の化学式は LiNi₀.₈Mn₀.₁Co₀.₁O₂（NMC811）なので、ニッケルの組成比は **0.8** です（ニッケル：マンガン：コバルト ＝ 8：1：1）。 | L7: 10-05
A8: 6 | B8: P4 | C8: 書式・文字装飾 | D8: 500サイクル後の容量維持率は何％ですか？ | E8: 92.4%（C₅₀₀÷C₁×100） | F8: 正解の要素がすべて含まれる=OK／一部のみ=部分／誤り・スライドにない内容を断定=NG | G8: 【下付き文字（数式）】P4 下付き文字を含む式 | H8: OK | I8: 92.4% | K8: 500サイクル後の容量維持率は92.4%です（スライド4：容量維持率 ＝ C₅₀₀ ÷ C₁ × 100 ＝ 92.4%。500サイクル目の放電容量が1サイクル目の92.4%）。 | L8: 10-06
A9: 7 | B9: P5 | C9: 図解・位置関係 | D9: TRLが最も低い要素技術と、そのレベルを答えてください。 | E9: シリコン系負極、TRL4 | F9: 正解の要素がすべて含まれる=OK／一部のみ=部分／誤り・スライドにない内容を断定=NG | G9: 【図形の長さ】P5 バーの長さと目盛（数値の記載なし） | H9: OK | I9: シリコン系負極、TRL4 | K9: TRLが最も低い要素技術は「シリコン系負極」で、レベルは「TRL4」です（スライド5）。 ※なお、資料の注記によると、TRLの値は図の棒の終点の位置から読み取ったもので、スライドに数値の記載はありません。 | L9: 10-07
A10: 8 | B10: P5 | C10: 図解・位置関係 | D10: TRL7に達している技術はどれですか？ | E10: 高ニッケル正極 | F10: 正解の要素がすべて含まれる=OK／一部のみ=部分／誤り・スライドにない内容を断定=NG | G10: 【図形の長さ】P5 バーの長さ | H10: OK | I10: 高ニッケル正極 | K10: TRL7に達している技術は「高ニッケル正極」です（スライド5）。 なお、TRLの値は図の棒の終点の位置から読み取ったもので、スライドに数値は書かれていません。 ほかの要素技術は、急速充電制御がTRL6、固体電解質がTRL5、シリコン系負極がTRL4です。 | L10: 10-08
A11: 9 | B11: P5 | C11: 図解・位置関係 | D11: 実用化判断の基準を満たしている技術をすべて答えてください。 | E11: 高ニッケル正極（TRL7）、急速充電制御（TRL6） | F11: 正解の要素がすべて含まれる=OK／一部のみ=部分／誤り・スライドにない内容を断定=NG | G11: 【図形の長さ】P5 基準線（TRL6）とバー | H11: OK | I11: 高ニッケル正極（TRL7）、急速充電制御（TRL6） | K11: 実用化判断の基準（TRL6以上）を満たしている技術は、次の2つです。 - 高ニッケル正極（TRL7） - 急速充電制御（TRL6） （スライド5「要素技術の成熟度（TRL）」より。固体電解質（TRL5）とシリコン系負極（TRL4）は基準未達です。なお、TRLの値は図の棒の終点の位置から読み取ったもので、スライドに数値の記載はありません。） | L11: 10-09
A12: 10 | B12: P6 | C12: 図解・位置関係 | D12: 第3世代セルの量産開始の前提となっているマイルストーンは何ですか？それはいつですか？ | E12: 固体電解質の量産技術の確立（2029年） | F12: 正解の要素がすべて含まれる=OK／一部のみ=部分／誤り・スライドにない内容を断定=NG | G12: 【図解（依存関係）】P6 赤矢印 | H12: OK | I12: 固体電解質の量産技術の確立（2029年） | K12: 第3世代セルの量産開始（2030年）の前提となっているマイルストーンは、材料レーンの「固体電解質の量産技術の確立」で、時期は2029年です（スライド6の赤矢印の前提関係による。年は図の位置から読み取ったもので、月の記載はありません）。 | L12: 10-10
A13: 11 | B13: P6 | C13: 図解・位置関係 | D13: 急速充電制御の実証は何年から何年まで行われますか？ | E13: 2028年〜2029年 | F13: 正解の要素がすべて含まれる=OK／一部のみ=部分／誤り・スライドにない内容を断定=NG | G13: 【位置（タイムライン）】P6 バーの位置 | H13: OK | I13: 2028年〜2029年 | K13: 急速充電制御の実証は、2028年から2029年まで行われます（スライド6「開発ロードマップ」の制御レーン）。なお、この期間は図中の位置から年単位で読み取ったもので、月の記載はありません。実証の後、2030年に製品搭載が予定されています。 | L13: 10-11
A14: 12 | B14: P7 | C14: 図解・位置関係 | D14: 交渉中（未契約）の提携先と、その内容を答えてください。 | E14: ミライ自動車、技術ライセンス（2027年度の契約を目指す） | F14: 正解の要素がすべて含まれる=OK／一部のみ=部分／誤り・スライドにない内容を断定=NG | G14: 【図解（線種）】P7 破線＋凡例 | H14: OK | I14: ミライ自動車、技術ライセンス（2027年度の契約を目指す） | K14: 交渉中（未契約）の提携先は「ミライ自動車」です。 - 内容：技術ライセンス（当社 → ミライ自動車への技術供与。量産後に自動車メーカーへ技術供与する位置づけ） - 契約状況：交渉中（提携関係図では破線で表示）。2027年度の契約を目指している。 （出典：スライド7「共同研究・提携体制」） | L14: 10-12
... A22: 20 | B22: — | C22: 記載なし | D22: 第3世代セルの販売価格（1kWhあたり）はいくらですか？ | E22: 記載なし | F22: 『記載なし』『資料からは分からない』=OK／推測と明示して答える=部分／値を断定=NG | G22: 【記載なし】全体 | H22: OK | I22: 記載なし | K22: 資料には、第3世代セルの販売価格（1kWhあたり）は記載されていません。 資料に含まれている第3世代セル関連の数値は、サイクル寿命（10,000回）、重量エネルギー密度（420 Wh/kg）、材料構成、層の厚み、開発予算（年度別・5年間合計84億円）などで、販売価格やkWhあたりのコストについての情報はありません。なお、販売開始は2031年の予定とされています（スライド6）。 | L22: 10-20
A24: 記入例（行1の場合）
H25: OK | I25: （LLMの回答の要点を記入）

Sheet 集計
A1: 集計（自動計算）
A2: 使用モデル | B2: claude-opus-5-5（1問ごとに新規サブエージェント）
A3: 入力方法（抽出テキスト／画像／ファイル直接など） | B3: 抽出テキスト（pptxを変換したMarkdownを入力。xlsx・正解は非提示）
A4: 正答率 = (OK + 0.5×部分) ÷ 判定記入数
A6: ファイル | B6: 問題数 | C6: OK | D6: 部分 | E6: NG | F6: 未記入 | G6: 正答率
A7: 06_新規出店計画 | B7: 20 | C7: =COUNTIF(06_新規出店計画!$H$3:$H$22,"OK") -> 20 | D7: =COUNTIF(06_新規出店計画!$H$3:$H$22,"部分") -> 0 | E7: =COUNTIF(06_新規出店計画!$H$3:$H$22,"NG") -> 0 | F7: =B7-SUM(C7:E7) -> 0 | G7: =IF(SUM(C7:E7)=0,"-",(C7+0.5*D7)/SUM(C7:E7)) -> 1
A8: 07_品質改善報告 | B8: 20 | C8: =COUNTIF(07_品質改善報告!$H$3:$H$22,"OK") -> 20 | D8: =COUNTIF(07_品質改善報告!$H$3:$H$22,"部分") -> 0 | E8: =COUNTIF(07_品質改善報告!$H$3:$H$22,"NG") -> 0 | F8: =B8-SUM(C8:E8) -> 0 | G8: =IF(SUM(C8:E8)=0,"-",(C8+0.5*D8)/SUM(C8:E8)) -> 1
A9: 08_デジタル広告 | B9: 20 | C9: =COUNTIF(08_デジタル広告!$H$3:$H$22,"OK") -> 20 | D9: =COUNTIF(08_デジタル広告!$H$3:$H$22,"部分") -> 0 | E9: =COUNTIF(08_デジタル広告!$H$3:$H$22,"NG") -> 0 | F9: =B9-SUM(C9:E9) -> 0 | G9: =IF(SUM(C9:E9)=0,"-",(C9+0.5*D9)/SUM(C9:E9)) -> 1
A10: 09_組織再編案 | B10: 20 | C10: =COUNTIF(09_組織再編案!$H$3:$H$22,"OK") -> 19 | D10: =COUNTIF(09_組織再編案!$H$3:$H$22,"部分") -> 0 | E10: =COUNTIF(09_組織再編案!$H$3:$H$22,"NG") -> 1 | F10: =B10-SUM(C10:E10) -> 0 | G10: =IF(SUM(C10:E10)=0,"-",(C10+0.5*D10)/SUM(C10:E10)) -> 0.95
A11: 10_技術ロードマップ | B11: 20 | C11: =COUNTIF(10_技術ロードマップ!$H$3:$H$22,"OK") -> 20 | D11: =COUNTIF(10_技術ロードマップ!$H$3:$H$22,"部分") -> 0 | E11: =COUNTIF(10_技術ロードマップ!$H$3:$H$22,"NG") -> 0 | F11: =B11-SUM(C11:E11) -> 0 | G11: =IF(SUM(C11:E11)=0,"-",(C11+0.5*D11)/SUM(C11:E11)) -> 1
A12: 合計 | B12: =SUM(B7:B11) -> 100 | C12: =SUM(C7:C11) -> 99 | D12: =SUM(D7:D11) -> 0 | E12: =SUM(E7:E11) -> 1 | F12: =SUM(F7:F11) -> 0 | G12: =IF(SUM(C12:E12)=0,"-",(C12+0.5*D12)/SUM(C12:E12)) -> 0.99
A14: 問題種別ごと（全ファイル合計）
A15: 問題種別 | B15: 問題数 | C15: OK | D15: 部分 | E15: NG | F15: 未記入 | G15: 正答率
A16: 書式・文字装飾 | B16: =COUNTIF(06_新規出店計画!$C$3:$C$22,$A16)+COUNTIF(07_品質改善報告!$C$3:$C$22,$A16)+COUNTIF(08_デジタル広告!$C$3:$C$22,$A16)+COUNTIF(09_組織再編案!$C$3:$C$22,$A16)+COUNTIF(10_技術ロードマップ!$C$3:$C$22,$A16) -> 13 | C16: =COUNTIFS(06_新規出店計画!$C$3:$C$22,$A16,06_新規出店計画!$H$3:$H$22,"OK")+COUNTIFS(07_品質改善報告!$C$3:$C$22,$A16,07_品質改善報告!$H$3:$H$22,"OK")+COUNTIFS(08_デジタル広告!$C$3:$C$22,$A16,08_デジタル広告!$H$3:$H$22,"OK")+COUNTIFS(09_組織再編案!$C$3:$C$22,$A16,09_組織再編案!$H$3:$H$22,"OK")+COUNTIFS(10_技術ロードマップ!$C$3:$C$22,$A16,10_技術ロードマップ!$H$3:$H$22,"OK") -> 13 | D16: =COUNTIFS(06_新規出店計画!$C$3:$C$22,$A16,06_新規出店計画!$H$3:$H$22,"部分")+COUNTIFS(07_品質改善報告!$C$3:$C$22,$A16,07_品質改善報告!$H$3:$H$22,"部分")+COUNTIFS(08_デジタル広告!$C$3:$C$22,$A16,08_デジタル広告!$H$3:$H$22,"部分")+COUNTIFS(09_組織再編案!$C$3:$C$22,$A16,09_組織再編案!$H$3:$H$22,"部分")+COUNTIFS(10_技術ロードマップ!$C$3:$C$22,$A16,10_技術ロードマップ!$H$3:$H$22,"部分") -> 0 | E16: =COUNTIFS(06_新規出店計画!$C$3:$C$22,$A16,06_新規出店計画!$H$3:$H$22,"NG")+COUNTIFS(07_品質改善報告!$C$3:$C$22,$A16,07_品質改善報告!$H$3:$H$22,"NG")+COUNTIFS(08_デジタル広告!$C$3:$C$22,$A16,08_デジタル広告!$H$3:$H$22,"NG")+COUNTIFS(09_組織再編案!$C$3:$C$22,$A16,09_組織再編案!$H$3:$H$22,"NG")+COUNTIFS(10_技術ロードマップ!$C$3:$C$22,$A16,10_技術ロードマップ!$H$3:$H$22,"NG") -> 0 | F16: =B16-SUM(C16:E16) -> 0 | G16: =IF(SUM(C16:E16)=0,"-",(C16+0.5*D16)/SUM(C16:E16)) -> 1
A17: グラフ | B17: =COUNTIF(06_新規出店計画!$C$3:$C$22,$A17)+COUNTIF(07_品質改善報告!$C$3:$C$22,$A17)+COUNTIF(08_デジタル広告!$C$3:$C$22,$A17)+COUNTIF(09_組織再編案!$C$3:$C$22,$A17)+COUNTIF(10_技術ロードマップ!$C$3:$C$22,$A17) -> 15 | C17: =COUNTIFS(06_新規出店計画!$C$3:$C$22,$A17,06_新規出店計画!$H$3:$H$22,"OK")+COUNTIFS(07_品質改善報告!$C$3:$C$22,$A17,07_品質改善報告!$H$3:$H$22,"OK")+COUNTIFS(08_デジタル広告!$C$3:$C$22,$A17,08_デジタル広告!$H$3:$H$22,"OK")+COUNTIFS(09_組織再編案!$C$3:$C$22,$A17,09_組織再編案!$H$3:$H$22,"OK")+COUNTIFS(10_技術ロードマップ!$C$3:$C$22,$A17,10_技術ロードマップ!$H$3:$H$22,"OK") -> 15 | D17: =COUNTIFS(06_新規出店計画!$C$3:$C$22,$A17,06_新規出店計画!$H$3:$H$22,"部分")+COUNTIFS(07_品質改善報告!$C$3:$C$22,$A17,07_品質改善報告!$H$3:$H$22,"部分")+COUNTIFS(08_デジタル広告!$C$3:$C$22,$A17,08_デジタル広告!$H$3:$H$22,"部分")+COUNTIFS(09_組織再編案!$C$3:$C$22,$A17,09_組織再編案!$H$3:$H$22,"部分")+COUNTIFS(10_技術ロードマップ!$C$3:$C$22,$A17,10_技術ロードマップ!$H$3:$H$22,"部分") -> 0 | E17: =COUNTIFS(06_新規出店計画!$C$3:$C$22,$A17,06_新規出店計画!$H$3:$H$22,"NG")+COUNTIFS(07_品質改善報告!$C$3:$C$22,$A17,07_品質改善報告!$H$3:$H$22,"NG")+COUNTIFS(08_デジタル広告!$C$3:$C$22,$A17,08_デジタル広告!$H$3:$H$22,"NG")+COUNTIFS(09_組織再編案!$C$3:$C$22,$A17,09_組織再編案!$H$3:$H$22,"NG")+COUNTIFS(10_技術ロードマップ!$C$3:$C$22,$A17,10_技術ロードマップ!$H$3:$H$22,"NG") -> 0 | F17: =B17-SUM(C17:E17) -> 0 | G17: =IF(SUM(C17:E17)=0,"-",(C17+0.5*D17)/SUM(C17:E17)) -> 1
A18: 画像 | B18: =COUNTIF(06_新規出店計画!$C$3:$C$22,$A18)+COUNTIF(07_品質改善報告!$C$3:$C$22,$A18)+COUNTIF(08_デジタル広告!$C$3:$C$22,$A18)+COUNTIF(09_組織再編案!$C$3:$C$22,$A18)+COUNTIF(10_技術ロードマップ!$C$3:$C$22,$A18) -> 16 | C18: =COUNTIFS(06_新規出店計画!$C$3:$C$22,$A18,06_新規出店計画!$H$3:$H$22,"OK")+COUNTIFS(07_品質改善報告!$C$3:$C$22,$A18,07_品質改善報告!$H$3:$H$22,"OK")+COUNTIFS(08_デジタル広告!$C$3:$C$22,$A18,08_デジタル広告!$H$3:$H$22,"OK")+COUNTIFS(09_組織再編案!$C$3:$C$22,$A18,09_組織再編案!$H$3:$H$22,"OK")+COUNTIFS(10_技術ロードマップ!$C$3:$C$22,$A18,10_技術ロードマップ!$H$3:$H$22,"OK") -> 16 | D18: =COUNTIFS(06_新規出店計画!$C$3:$C$22,$A18,06_新規出店計画!$H$3:$H$22,"部分")+COUNTIFS(07_品質改善報告!$C$3:$C$22,$A18,07_品質改善報告!$H$3:$H$22,"部分")+COUNTIFS(08_デジタル広告!$C$3:$C$22,$A18,08_デジタル広告!$H$3:$H$22,"部分")+COUNTIFS(09_組織再編案!$C$3:$C$22,$A18,09_組織再編案!$H$3:$H$22,"部分")+COUNTIFS(10_技術ロードマップ!$C$3:$C$22,$A18,10_技術ロードマップ!$H$3:$H$22,"部分") -> 0 | E18: =COUNTIFS(06_新規出店計画!$C$3:$C$22,$A18,06_新規出店計画!$H$3:$H$22,"NG")+COUNTIFS(07_品質改善報告!$C$3:$C$22,$A18,07_品質改善報告!$H$3:$H$22,"NG")+COUNTIFS(08_デジタル広告!$C$3:$C$22,$A18,08_デジタル広告!$H$3:$H$22,"NG")+COUNTIFS(09_組織再編案!$C$3:$C$22,$A18,09_組織再編案!$H$3:$H$22,"NG")+COUNTIFS(10_技術ロードマップ!$C$3:$C$22,$A18,10_技術ロードマップ!$H$3:$H$22,"NG") -> 0 | F18: =B18-SUM(C18:E18) -> 0 | G18: =IF(SUM(C18:E18)=0,"-",(C18+0.5*D18)/SUM(C18:E18)) -> 1
A19: スライド上に見えない情報 | B19: =COUNTIF(06_新規出店計画!$C$3:$C$22,$A19)+COUNTIF(07_品質改善報告!$C$3:$C$22,$A19)+COUNTIF(08_デジタル広告!$C$3:$C$22,$A19)+COUNTIF(09_組織再編案!$C$3:$C$22,$A19)+COUNTIF(10_技術ロードマップ!$C$3:$C$22,$A19) -> 11 | C19: =COUNTIFS(06_新規出店計画!$C$3:$C$22,$A19,06_新規出店計画!$H$3:$H$22,"OK")+COUNTIFS(07_品質改善報告!$C$3:$C$22,$A19,07_品質改善報告!$H$3:$H$22,"OK")+COUNTIFS(08_デジタル広告!$C$3:$C$22,$A19,08_デジタル広告!$H$3:$H$22,"OK")+COUNTIFS(09_組織再編案!$C$3:$C$22,$A19,09_組織再編案!$H$3:$H$22,"OK")+COUNTIFS(10_技術ロードマップ!$C$3:$C$22,$A19,10_技術ロードマップ!$H$3:$H$22,"OK") -> 10 | D19: =COUNTIFS(06_新規出店計画!$C$3:$C$22,$A19,06_新規出店計画!$H$3:$H$22,"部分")+COUNTIFS(07_品質改善報告!$C$3:$C$22,$A19,07_品質改善報告!$H$3:$H$22,"部分")+COUNTIFS(08_デジタル広告!$C$3:$C$22,$A19,08_デジタル広告!$H$3:$H$22,"部分")+COUNTIFS(09_組織再編案!$C$3:$C$22,$A19,09_組織再編案!$H$3:$H$22,"部分")+COUNTIFS(10_技術ロードマップ!$C$3:$C$22,$A19,10_技術ロードマップ!$H$3:$H$22,"部分") -> 0 | E19: =COUNTIFS(06_新規出店計画!$C$3:$C$22,$A19,06_新規出店計画!$H$3:$H$22,"NG")+COUNTIFS(07_品質改善報告!$C$3:$C$22,$A19,07_品質改善報告!$H$3:$H$22,"NG")+COUNTIFS(08_デジタル広告!$C$3:$C$22,$A19,08_デジタル広告!$H$3:$H$22,"NG")+COUNTIFS(09_組織再編案!$C$3:$C$22,$A19,09_組織再編案!$H$3:$H$22,"NG")+COUNTIFS(10_技術ロードマップ!$C$3:$C$22,$A19,10_技術ロードマップ!$H$3:$H$22,"NG") -> 1 | F19: =B19-SUM(C19:E19) -> 0 | G19: =IF(SUM(C19:E19)=0,"-",(C19+0.5*D19)/SUM(C19:E19)) -> 0.90909091
A20: 表 | B20: =COUNTIF(06_新規出店計画!$C$3:$C$22,$A20)+COUNTIF(07_品質改善報告!$C$3:$C$22,$A20)+COUNTIF(08_デジタル広告!$C$3:$C$22,$A20)+COUNTIF(09_組織再編案!$C$3:$C$22,$A20)+COUNTIF(10_技術ロードマップ!$C$3:$C$22,$A20) -> 8 | C20: =COUNTIFS(06_新規出店計画!$C$3:$C$22,$A20,06_新規出店計画!$H$3:$H$22,"OK")+COUNTIFS(07_品質改善報告!$C$3:$C$22,$A20,07_品質改善報告!$H$3:$H$22,"OK")+COUNTIFS(08_デジタル広告!$C$3:$C$22,$A20,08_デジタル広告!$H$3:$H$22,"OK")+COUNTIFS(09_組織再編案!$C$3:$C$22,$A20,09_組織再編案!$H$3:$H$22,"OK")+COUNTIFS(10_技術ロードマップ!$C$3:$C$22,$A20,10_技術ロードマップ!$H$3:$H$22,"OK") -> 8 | D20: =COUNTIFS(06_新規出店計画!$C$3:$C$22,$A20,06_新規出店計画!$H$3:$H$22,"部分")+COUNTIFS(07_品質改善報告!$C$3:$C$22,$A20,07_品質改善報告!$H$3:$H$22,"部分")+COUNTIFS(08_デジタル広告!$C$3:$C$22,$A20,08_デジタル広告!$H$3:$H$22,"部分")+COUNTIFS(09_組織再編案!$C$3:$C$22,$A20,09_組織再編案!$H$3:$H$22,"部分")+COUNTIFS(10_技術ロードマップ!$C$3:$C$22,$A20,10_技術ロードマップ!$H$3:$H$22,"部分") -> 0 | E20: =COUNTIFS(06_新規出店計画!$C$3:$C$22,$A20,06_新規出店計画!$H$3:$H$22,"NG")+COUNTIFS(07_品質改善報告!$C$3:$C$22,$A20,07_品質改善報告!$H$3:$H$22,"NG")+COUNTIFS(08_デジタル広告!$C$3:$C$22,$A20,08_デジタル広告!$H$3:$H$22,"NG")+COUNTIFS(09_組織再編案!$C$3:$C$22,$A20,09_組織再編案!$H$3:$H$22,"NG")+COUNTIFS(10_技術ロードマップ!$C$3:$C$22,$A20,10_技術ロードマップ!$H$3:$H$22,"NG") -> 0 | F20: =B20-SUM(C20:E20) -> 0 | G20: =IF(SUM(C20:E20)=0,"-",(C20+0.5*D20)/SUM(C20:E20)) -> 1
A21: 計算 | B21: =COUNTIF(06_新規出店計画!$C$3:$C$22,$A21)+COUNTIF(07_品質改善報告!$C$3:$C$22,$A21)+COUNTIF(08_デジタル広告!$C$3:$C$22,$A21)+COUNTIF(09_組織再編案!$C$3:$C$22,$A21)+COUNTIF(10_技術ロードマップ!$C$3:$C$22,$A21) -> 10 | C21: =COUNTIFS(06_新規出店計画!$C$3:$C$22,$A21,06_新規出店計画!$H$3:$H$22,"OK")+COUNTIFS(07_品質改善報告!$C$3:$C$22,$A21,07_品質改善報告!$H$3:$H$22,"OK")+COUNTIFS(08_デジタル広告!$C$3:$C$22,$A21,08_デジタル広告!$H$3:$H$22,"OK")+COUNTIFS(09_組織再編案!$C$3:$C$22,$A21,09_組織再編案!$H$3:$H$22,"OK")+COUNTIFS(10_技術ロードマップ!$C$3:$C$22,$A21,10_技術ロードマップ!$H$3:$H$22,"OK") -> 10 | D21: =COUNTIFS(06_新規出店計画!$C$3:$C$22,$A21,06_新規出店計画!$H$3:$H$22,"部分")+COUNTIFS(07_品質改善報告!$C$3:$C$22,$A21,07_品質改善報告!$H$3:$H$22,"部分")+COUNTIFS(08_デジタル広告!$C$3:$C$22,$A21,08_デジタル広告!$H$3:$H$22,"部分")+COUNTIFS(09_組織再編案!$C$3:$C$22,$A21,09_組織再編案!$H$3:$H$22,"部分")+COUNTIFS(10_技術ロードマップ!$C$3:$C$22,$A21,10_技術ロードマップ!$H$3:$H$22,"部分") -> 0 | E21: =COUNTIFS(06_新規出店計画!$C$3:$C$22,$A21,06_新規出店計画!$H$3:$H$22,"NG")+COUNTIFS(07_品質改善報告!$C$3:$C$22,$A21,07_品質改善報告!$H$3:$H$22,"NG")+COUNTIFS(08_デジタル広告!$C$3:$C$22,$A21,08_デジタル広告!$H$3:$H$22,"NG")+COUNTIFS(09_組織再編案!$C$3:$C$22,$A21,09_組織再編案!$H$3:$H$22,"NG")+COUNTIFS(10_技術ロードマップ!$C$3:$C$22,$A21,10_技術ロードマップ!$H$3:$H$22,"NG") -> 0 | F21: =B21-SUM(C21:E21) -> 0 | G21: =IF(SUM(C21:E21)=0,"-",(C21+0.5*D21)/SUM(C21:E21)) -> 1
A22: 図解・位置関係 | B22: =COUNTIF(06_新規出店計画!$C$3:$C$22,$A22)+COUNTIF(07_品質改善報告!$C$3:$C$22,$A22)+COUNTIF(08_デジタル広告!$C$3:$C$22,$A22)+COUNTIF(09_組織再編案!$C$3:$C$22,$A22)+COUNTIF(10_技術ロードマップ!$C$3:$C$22,$A22) -> 23 | C22: =COUNTIFS(06_新規出店計画!$C$3:$C$22,$A22,06_新規出店計画!$H$3:$H$22,"OK")+COUNTIFS(07_品質改善報告!$C$3:$C$22,$A22,07_品質改善報告!$H$3:$H$22,"OK")+COUNTIFS(08_デジタル広告!$C$3:$C$22,$A22,08_デジタル広告!$H$3:$H$22,"OK")+COUNTIFS(09_組織再編案!$C$3:$C$22,$A22,09_組織再編案!$H$3:$H$22,"OK")+COUNTIFS(10_技術ロードマップ!$C$3:$C$22,$A22,10_技術ロードマップ!$H$3:$H$22,"OK") -> 23 | D22: =COUNTIFS(06_新規出店計画!$C$3:$C$22,$A22,06_新規出店計画!$H$3:$H$22,"部分")+COUNTIFS(07_品質改善報告!$C$3:$C$22,$A22,07_品質改善報告!$H$3:$H$22,"部分")+COUNTIFS(08_デジタル広告!$C$3:$C$22,$A22,08_デジタル広告!$H$3:$H$22,"部分")+COUNTIFS(09_組織再編案!$C$3:$C$22,$A22,09_組織再編案!$H$3:$H$22,"部分")+COUNTIFS(10_技術ロードマップ!$C$3:$C$22,$A22,10_技術ロードマップ!$H$3:$H$22,"部分") -> 0 | E22: =COUNTIFS(06_新規出店計画!$C$3:$C$22,$A22,06_新規出店計画!$H$3:$H$22,"NG")+COUNTIFS(07_品質改善報告!$C$3:$C$22,$A22,07_品質改善報告!$H$3:$H$22,"NG")+COUNTIFS(08_デジタル広告!$C$3:$C$22,$A22,08_デジタル広告!$H$3:$H$22,"NG")+COUNTIFS(09_組織再編案!$C$3:$C$22,$A22,09_組織再編案!$H$3:$H$22,"NG")+COUNTIFS(10_技術ロードマップ!$C$3:$C$22,$A22,10_技術ロードマップ!$H$3:$H$22,"NG") -> 0 | F22: =B22-SUM(C22:E22) -> 0 | G22: =IF(SUM(C22:E22)=0,"-",(C22+0.5*D22)/SUM(C22:E22)) -> 1
A23: 記載なし | B23: =COUNTIF(06_新規出店計画!$C$3:$C$22,$A23)+COUNTIF(07_品質改善報告!$C$3:$C$22,$A23)+COUNTIF(08_デジタル広告!$C$3:$C$22,$A23)+COUNTIF(09_組織再編案!$C$3:$C$22,$A23)+COUNTIF(10_技術ロードマップ!$C$3:$C$22,$A23) -> 3 | C23: =COUNTIFS(06_新規出店計画!$C$3:$C$22,$A23,06_新規出店計画!$H$3:$H$22,"OK")+COUNTIFS(07_品質改善報告!$C$3:$C$22,$A23,07_品質改善報告!$H$3:$H$22,"OK")+COUNTIFS(08_デジタル広告!$C$3:$C$22,$A23,08_デジタル広告!$H$3:$H$22,"OK")+COUNTIFS(09_組織再編案!$C$3:$C$22,$A23,09_組織再編案!$H$3:$H$22,"OK")+COUNTIFS(10_技術ロードマップ!$C$3:$C$22,$A23,10_技術ロードマップ!$H$3:$H$22,"OK") -> 3 | D23: =COUNTIFS(06_新規出店計画!$C$3:$C$22,$A23,06_新規出店計画!$H$3:$H$22,"部分")+COUNTIFS(07_品質改善報告!$C$3:$C$22,$A23,07_品質改善報告!$H$3:$H$22,"部分")+COUNTIFS(08_デジタル広告!$C$3:$C$22,$A23,08_デジタル広告!$H$3:$H$22,"部分")+COUNTIFS(09_組織再編案!$C$3:$C$22,$A23,09_組織再編案!$H$3:$H$22,"部分")+COUNTIFS(10_技術ロードマップ!$C$3:$C$22,$A23,10_技術ロードマップ!$H$3:$H$22,"部分") -> 0 | E23: =COUNTIFS(06_新規出店計画!$C$3:$C$22,$A23,06_新規出店計画!$H$3:$H$22,"NG")+COUNTIFS(07_品質改善報告!$C$3:$C$22,$A23,07_品質改善報告!$H$3:$H$22,"NG")+COUNTIFS(08_デジタル広告!$C$3:$C$22,$A23,08_デジタル広告!$H$3:$H$22,"NG")+COUNTIFS(09_組織再編案!$C$3:$C$22,$A23,09_組織再編案!$H$3:$H$22,"NG")+COUNTIFS(10_技術ロードマップ!$C$3:$C$22,$A23,10_技術ロードマップ!$H$3:$H$22,"NG") -> 0 | F23: =B23-SUM(C23:E23) -> 0 | G23: =IF(SUM(C23:E23)=0,"-",(C23+0.5*D23)/SUM(C23:E23)) -> 1
A24: テキスト | B24: =COUNTIF(06_新規出店計画!$C$3:$C$22,$A24)+COUNTIF(07_品質改善報告!$C$3:$C$22,$A24)+COUNTIF(08_デジタル広告!$C$3:$C$22,$A24)+COUNTIF(09_組織再編案!$C$3:$C$22,$A24)+COUNTIF(10_技術ロードマップ!$C$3:$C$22,$A24) -> 1 | C24: =COUNTIFS(06_新規出店計画!$C$3:$C$22,$A24,06_新規出店計画!$H$3:$H$22,"OK")+COUNTIFS(07_品質改善報告!$C$3:$C$22,$A24,07_品質改善報告!$H$3:$H$22,"OK")+COUNTIFS(08_デジタル広告!$C$3:$C$22,$A24,08_デジタル広告!$H$3:$H$22,"OK")+COUNTIFS(09_組織再編案!$C$3:$C$22,$A24,09_組織再編案!$H$3:$H$22,"OK")+COUNTIFS(10_技術ロードマップ!$C$3:$C$22,$A24,10_技術ロードマップ!$H$3:$H$22,"OK") -> 1 | D24: =COUNTIFS(06_新規出店計画!$C$3:$C$22,$A24,06_新規出店計画!$H$3:$H$22,"部分")+COUNTIFS(07_品質改善報告!$C$3:$C$22,$A24,07_品質改善報告!$H$3:$H$22,"部分")+COUNTIFS(08_デジタル広告!$C$3:$C$22,$A24,08_デジタル広告!$H$3:$H$22,"部分")+COUNTIFS(09_組織再編案!$C$3:$C$22,$A24,09_組織再編案!$H$3:$H$22,"部分")+COUNTIFS(10_技術ロードマップ!$C$3:$C$22,$A24,10_技術ロードマップ!$H$3:$H$22,"部分") -> 0 | E24: =COUNTIFS(06_新規出店計画!$C$3:$C$22,$A24,06_新規出店計画!$H$3:$H$22,"NG")+COUNTIFS(07_品質改善報告!$C$3:$C$22,$A24,07_品質改善報告!$H$3:$H$22,"NG")+COUNTIFS(08_デジタル広告!$C$3:$C$22,$A24,08_デジタル広告!$H$3:$H$22,"NG")+COUNTIFS(09_組織再編案!$C$3:$C$22,$A24,09_組織再編案!$H$3:$H$22,"NG")+COUNTIFS(10_技術ロードマップ!$C$3:$C$22,$A24,10_技術ロードマップ!$H$3:$H$22,"NG") -> 0 | F24: =B24-SUM(C24:E24) -> 0 | G24: =IF(SUM(C24:E24)=0,"-",(C24+0.5*D24)/SUM(C24:E24)) -> 1
