Workbook

Sheet 実施方法
A2: LLMスライド読解テスト：実施方法
A3: 対象：5ファイル×10枚、各20問、合計100問。すべて架空の業務データ。
A4: 入力：対象PPTXと「問題」シートの質問のみをLLMへ渡す。正解表は渡さない。
A5: 共通指示：資料のみを根拠に回答し、参照スライド番号と計算式を示す。記載がなければ不明と答える。
A6: 推奨：質問ごとに新しい会話で実施。モデル名・版・読込方式・実施日を別途記録する。
A7: 採点：2＝必須要素が一致、1＝一部正しいが不足、0＝誤答・根拠のない断定・未回答。各問2点、各資料40点。
A8: 数値：同値の単位換算・言い換えを許容。丸め指定があればその精度で照合する。
A9: 回答不能問題：不明／未確定と理由を述べた場合2点。具体値を推測して断定した場合0点。
A10: 資料番号01～05がPowerPointファイルの先頭番号に対応。表紙をスライド1として数える。
A11: 正解表のLLM回答・得点・評価メモ欄を記録用に使用。得点は手動評価。

Sheet 01_問題
A2: 生成AI導入提案：テスト問題（LLM入力用）
A4: ID | B4: 質問
A5: 01-Q01 | B5: この提案の作成部署と提案責任者は誰ですか。
A6: 01-Q02 | B6: 試行対象の部署・人数・期間を答えてください。
A7: 01-Q03 | B7: 最も月間工数が大きい業務と、その工数を答えてください。
A8: 01-Q04 | B8: 規程確認の月間工数を件数と対応時間から計算してください。
A9: 01-Q05 | B9: 案件情報照会と顧客への自動回答は今回の対象ですか。
A10: 01-Q06 | B10: 製品FAQの件数・更新責任者・更新頻度を答えてください。
A11: 01-Q07 | B11: 検索から回答利用までに行う情報保護策を2つ挙げてください。
A12: 01-Q08 | B12: 回答の根拠が不足する場合はどう処理しますか。
A13: 01-Q09 | B13: B案がA案より優れる権限制御上の点は何ですか。
A14: 01-Q10 | B14: B案とA案の初期費用差はいくらですか。
A15: 01-Q11 | B15: 導入後に残る対象業務の月間工数はいくらですか。
... A24: 01-Q20 | B24: 試行予算の決裁者と本番展開を判断する評価会の日付を答えてください。

Sheet 01_正解表
A2: 生成AI導入提案：期待回答・評価記録
A4: ID | B4: 分類 | C4: 質問 | D4: 期待回答・採点必須要素 | E4: 参照スライド | F4: LLM回答 | G4: 得点（0～2） | H4: 評価メモ | I4: 判定 | J4: 生値ファイル
A5: 01-Q01 | B5: 事実抽出 | C5: この提案の作成部署と提案責任者は誰ですか。 | D5: 業務改革室、佐藤 遥。 | E5: 1 | F5: 作成部署は業務改革室、提案責任者は佐藤 遥です（スライド1）。 | G5: 2 | H5: 必須要素がすべて一致。 | I5: =IF(G5="","対象外",IF(G5=2,"正解",IF(G5=1,"部分正解","誤答"))) -> 正解 | J5: /tmp/out/01-Q01.txt
A6: 01-Q02 | B6: 事実抽出 | C6: 試行対象の部署・人数・期間を答えてください。 | D6: 営業部80名、2026年11月2日～12月25日。 | E6: 2 | F6: 試行対象は営業部の80名で、試行期間は2026年11月2日～12月25日です。対象業務は社内規程と製品FAQの検索です（スライド2）。このうち80名が実際に利用して効果を測るのは12月7日～12月18日で、12月25日の評価会で本番展開するかどうかを決めます（スライド8）。 | G6: 2 | H6: 必須要素がすべて一致。 | I6: =IF(G6="","対象外",IF(G6=2,"正解",IF(G6=1,"部分正解","誤答"))) -> 正解 | J6: /tmp/out/01-Q02.txt
A7: 01-Q03 | B7: 表の読解 | C7: 最も月間工数が大きい業務と、その工数を答えてください。 | D7: 製品FAQ、300時間／月。 | E7: 3 | F7: 最も月間工数が大きい業務は「製品FAQ」で、月間工数は300時間です（月間900件×平均20分÷60。スライド3より）。 | G7: 2 | H7: 必須要素がすべて一致。 | I7: =IF(G7="","対象外",IF(G7=2,"正解",IF(G7=1,"部分正解","誤答"))) -> 正解 | J7: /tmp/out/01-Q03.txt
A8: 01-Q04 | B8: 計算 | C8: 規程確認の月間工数を件数と対応時間から計算してください。 | D8: 600件×12分÷60＝120時間／月。 | E8: 3 | F8: 規程確認の月間工数は120時間です。 計算：600件 × 12分 = 7,200分、7,200分 ÷ 60 = 120時間 根拠：スライド3の表（規程確認：月間件数600件、平均対応時間12分）と、注記「工数は件数×分÷60」。計算結果は表の月間工数欄の120時間と一致します。 | G8: 2 | H8: 必須要素がすべて一致。 | I8: =IF(G8="","対象外",IF(G8=2,"正解",IF(G8=1,"部分正解","誤答"))) -> 正解 | J8: /tmp/out/01-Q04.txt
A9: 01-Q05 | B9: 範囲・例外 | C9: 案件情報照会と顧客への自動回答は今回の対象ですか。 | D9: どちらも対象外。 | E9: 2,3 | F9: いいえ、どちらも今回の対象外です。 - 案件情報照会：スライド3の注記に「案件情報照会は今回の導入対象外」とあります。スライド4の表でも、案件情報（600件、営業企画部）の更新頻度は「対象外」です。 - 顧客への自動回答：スライド2の要点4に「顧客への自動回答と人事評価は対象外」とあります。あわせてスライド5では、回答を社外へ送る前に人が確認することになっています。 今回の対象は、営業部80名による社内規程と製品FAQの検索です（スライド2）。このため、削減効果の試算もこの2業務の月420時間だけを基準にしています（スライド7）。 | G9: 2 | H9: 必須要素がすべて一致。 | I9: =IF(G9="","対象外",IF(G9=2,"正解",IF(G9=1,"部分正解","誤答"))) -> 正解 | J9: /tmp/out/01-Q05.txt
A10: 01-Q06 | B10: 表の読解 | C10: 製品FAQの件数・更新責任者・更新頻度を答えてください。 | D10: 380件、商品企画部、週1回。 | E10: 4 | F10: 製品FAQ（対象文書）：件数 380件、更新責任者 商品企画部、更新頻度 週1回 | G10: 2 | H10: 必須要素がすべて一致。 | I10: =IF(G10="","対象外",IF(G10=2,"正解",IF(G10=1,"部分正解","誤答"))) -> 正解 | J10: /tmp/out/01-Q06.txt
A11: 01-Q07 | B11: 手順 | C11: 検索から回答利用までに行う情報保護策を2つ挙げてください。 | D11: 閲覧権限で検索結果を制限する。社外送信前に人が確認する。 | E11: 5 | F11: 1. 検索時：閲覧権限で検索結果を制限し、社員の権限内の文書だけを検索する。 2. 回答利用時：社外へ送信する前に、人（社員）が根拠を確認する。 （出典：スライド5「回答までの処理と責任分担」） | G11: 2 | H11: 必須要素がすべて一致。 | I11: =IF(G11="","対象外",IF(G11=2,"正解",IF(G11=1,"部分正解","誤答"))) -> 正解 | J11: /tmp/out/01-Q07.txt
A12: 01-Q08 | B12: 条件判断 | C12: 回答の根拠が不足する場合はどう処理しますか。 | D12: 回答を保留する。 | E12: 5 | F12: 根拠が不足する場合は、AIは回答を保留します（スライド5「回答までの処理と責任分担」の手順3「根拠に沿った回答案を生成」の統制として「根拠不足なら回答を保留」と記載）。 あわせて、回答には参照文書名・版・該当箇所を表示し、社員が根拠を確認したうえで利用します。社外へ送る前には人が確認します（スライド5、手順4）。 | G12: 2 | H12: 必須要素がすべて一致。 | I12: =IF(G12="","対象外",IF(G12=2,"正解",IF(G12=1,"部分正解","誤答"))) -> 正解 | J12: /tmp/out/01-Q08.txt
A13: 01-Q09 | B13: 比較 | C13: B案がA案より優れる権限制御上の点は何ですか。 | D13: B案は文書別の権限制御に対応し、A案は不足する。 | E13: 6 | F13: B案（文書検索連携）は文書別の権限制御に対応している点がA案より優れています。A案（汎用チャット）は「文書別の権限制御が不足」と評価されています（スライド6）。B案では、社員の閲覧権限に合わせて検索結果を絞り込み、権限内の文書だけを検索します（スライド5）。 | G13: 2 | H13: 必須要素がすべて一致。 | I13: =IF(G13="","対象外",IF(G13=2,"正解",IF(G13=1,"部分正解","誤答"))) -> 正解 | J13: /tmp/out/01-Q09.txt
A14: 01-Q10 | B14: 計算 | C14: B案とA案の初期費用差はいくらですか。 | D14: 240－80＝160万円。 | E14: 6 | F14: B案とA案の初期費用差は160万円です（B案240万円－A案80万円、いずれも税抜の概算。スライド6「導入方式の比較」より。B案の240万円には評価・研修費を含みます）。 | G14: 2 | H14: 必須要素がすべて一致。 | I14: =IF(G14="","対象外",IF(G14=2,"正解",IF(G14=1,"部分正解","誤答"))) -> 正解 | J14: /tmp/out/01-Q10.txt
A15: 01-Q11 | B15: グラフ読解 | C15: 導入後に残る対象業務の月間工数はいくらですか。 | D15: 180時間／月。 | E15: 7 | F15: 導入後に残る対象業務の月間工数は180時間です。 根拠： - スライド7のグラフ「導入前後の月間工数（対象業務のみ）」で、導入後の値は180時間です。 - 計算でも同じ値になります。スライド3の対象業務は規程確認120時間と製品FAQ300時間で、合計420時間です（案件情報照会180時間は対象外）。ここから削減想定の240時間を引くと、420時間－240時間＝180時間です。 注意：この値は試算です（スライド7の注記）。 | G15: 2 | H15: 必須要素がすべて一致。 | I15: =IF(G15="","対象外",IF(G15=2,"正解",IF(G15=1,"部分正解","誤答"))) -> 正解 | J15: /tmp/out/01-Q11.txt
A16: 01-Q12 | B16: 計算 | C16: 対象業務の工数削減率を小数第1位まで求めてください。 | D16: (420－180)÷420×100＝57.1%。 | E16: 7 | F16: 対象業務の工数削減率は約57.1%です。 計算：削減工数240時間 ÷ 導入前の対象業務工数420時間 × 100 = 57.142…% → 57.1% 根拠： - スライド7：導入前420時間、導入後180時間、削減想定240時間／月 - スライド3：対象業務は規程確認120時間＋製品FAQ300時間＝420時間（案件情報照会180時間は導入対象外のため除外） 注記：全体600時間を分母にすると40.0%になりますが、質問は「対象業務の」削減率のため分母は420時間です。また、この57.1%は月間工数の削減率です。スライド9の判定基準「平均対応時間削減率40%以上」とは指標が異なります。 | G16: 2 | H16: 必須要素がすべて一致。 | I16: =IF(G16="","対象外",IF(G16=2,"正解",IF(G16=1,"部分正解","誤答"))) -> 正解 | J16: /tmp/out/01-Q12.txt
... A24: 01-Q20 | B24: 複数スライド | C24: 試行予算の決裁者と本番展開を判断する評価会の日付を答えてください。 | D24: 経営企画担当役員、2026年12月25日。 | E24: 8,10 | F24: 試行予算の決裁者は経営企画担当役員です（スライド10）。本番展開の可否を決める評価会は2026年12月25日に開かれます（スライド8）。 | G24: 2 | H24: 必須要素がすべて一致。 | I24: =IF(G24="","対象外",IF(G24=2,"正解",IF(G24=1,"部分正解","誤答"))) -> 正解 | J24: /tmp/out/01-Q20.txt
F26: 合計得点 | G26: =SUM(G5:G24) -> 40
F27: 正解数（2点） | G27: =COUNTIF(I5:I24,"正解") -> 20
F28: 対象外 | G28: =COUNTIF(I5:I24,"対象外") -> 0

Sheet 02_問題
A2: システム開発進捗報告：テスト問題（LLM入力用）
A4: ID | B4: 質問
A5: 02-Q01 | B5: 報告基準日とPMを答えてください。
A6: 02-Q02 | B6: 総合判定と公開予定日を答えてください。
A7: 02-Q03 | B7: 総合進捗の計画との差をポイントで答えてください。
A8: 02-Q04 | B8: 計画との差が最も大きい工程はどれですか。
A9: 02-Q05 | B9: 総合進捗62%を工程別実績の単純平均で再現できますか。
A10: 02-Q06 | B10: 未解決不具合が最も多かった日と件数を答えてください。
A11: 02-Q07 | B11: 10月2日から23日までの残件数の増減を答えてください。
A12: 02-Q08 | B12: 重大不具合の残件数、期限、担当を答えてください。
A13: 02-Q09 | B13: 重大と高の不具合は合計何件ですか。
A14: 02-Q10 | B14: CR-07の取込上限は当初の何倍になりますか。
A15: 02-Q11 | B15: 報告基準日時点でCR-07は承認済みですか。
... A24: 02-Q20 | B24: 外部API提供会社の正式名称は何ですか。

Sheet 02_正解表
A2: システム開発進捗報告：期待回答・評価記録
A4: ID | B4: 分類 | C4: 質問 | D4: 期待回答・採点必須要素 | E4: 参照スライド | F4: LLM回答 | G4: 得点（0～2） | H4: 評価メモ | I4: 判定 | J4: 生値ファイル
A5: 02-Q01 | B5: 事実抽出 | C5: 報告基準日とPMを答えてください。 | D5: 2026年10月23日、田中 健。 | E5: 1 | F5: 報告基準日：2026年10月23日 PM（プロジェクトマネージャー）：田中 健 | G5: 2 | H5: 必須要素がすべて一致。 | I5: =IF(G5="","対象外",IF(G5=2,"正解",IF(G5=1,"部分正解","誤答"))) -> 正解 | J5: /tmp/out/02-Q01.txt
A6: 02-Q02 | B6: 事実抽出 | C6: 総合判定と公開予定日を答えてください。 | D6: 黄、2026年12月14日。 | E6: 2 | F6: 総合判定は「黄」、公開予定日は2026年12月14日（維持）です。 （根拠：スライド2「総合判定は黄、公開予定日は維持」、要点1「公開予定日：2026年12月14日」。報告基準日は2026年10月23日） | G6: 2 | H6: 必須要素がすべて一致。 | I6: =IF(G6="","対象外",IF(G6=2,"正解",IF(G6=1,"部分正解","誤答"))) -> 正解 | J6: /tmp/out/02-Q02.txt
A7: 02-Q03 | B7: 計算 | C7: 総合進捗の計画との差をポイントで答えてください。 | D7: 62－70＝マイナス8ポイント。 | E7: 2 | F7: 計画比8ポイントの遅れ（実績62%、計画70%。2026年10月23日時点） | G7: 2 | H7: 必須要素がすべて一致。 | I7: =IF(G7="","対象外",IF(G7=2,"正解",IF(G7=1,"部分正解","誤答"))) -> 正解 | J7: /tmp/out/02-Q03.txt
A8: 02-Q04 | B8: 表の読解 | C8: 計画との差が最も大きい工程はどれですか。 | D8: 結合試験。計画30%に対して実績10%で20ポイント差。 | E8: 3 | F8: 計画との差が最も大きい工程は「結合試験」です。計画30%に対して実績は10%で、差は20ポイントです（スライド3）。 参考として、他の工程の差は次のとおりです。 - 開発：計画80%、実績65%で、差は15ポイント - 要件定義・基本設計：計画100%、実績100%で、差はなし なお、結合試験の状況欄には「環境準備済み」と書かれています。 | G8: 2 | H8: 必須要素がすべて一致。 | I8: =IF(G8="","対象外",IF(G8=2,"正解",IF(G8=1,"部分正解","誤答"))) -> 正解 | J8: /tmp/out/02-Q04.txt
A9: 02-Q05 | B9: 注記 | C9: 総合進捗62%を工程別実績の単純平均で再現できますか。 | D9: できない。総合進捗は成果物の重み付き集計。 | E9: 3 | F9: いいえ、再現できません。 スライド3の工程別実績（要件定義100%、基本設計100%、開発65%、結合試験10%）を単純平均すると、(100＋100＋65＋10)÷4＝68.75%となり、総合進捗62%とは一致しません。参考までに計画値も単純平均すると(100＋100＋80＋30)÷4＝77.5%で、スライド2の計画70%とも一致しません。 スライド3の注記に「総合進捗62%は別途定めた成果物の重み付き集計。表の単純平均ではない。」と明記されています。62%は単純平均ではなく、成果物ごとの重み付けによる集計値です。ただし、その重み（各工程の比重や成果物件数）は資料に記載されていないため、資料の情報だけでは62%を再計算して検証することはできません。 | G9: 2 | H9: 必須要素がすべて一致。 | I9: =IF(G9="","対象外",IF(G9=2,"正解",IF(G9=1,"部分正解","誤答"))) -> 正解 | J9: /tmp/out/02-Q05.txt
A10: 02-Q06 | B10: グラフ読解 | C10: 未解決不具合が最も多かった日と件数を答えてください。 | D10: 2026年10月16日、31件。 | E10: 4 | F10: 2026年10月16日（金）の31件です。 | G10: 2 | H10: 必須要素がすべて一致。 | I10: =IF(G10="","対象外",IF(G10=2,"正解",IF(G10=1,"部分正解","誤答"))) -> 正解 | J10: /tmp/out/02-Q06.txt
A11: 02-Q07 | B11: 計算 | C11: 10月2日から23日までの残件数の増減を答えてください。 | D11: 18件から28件で10件増加。 | E11: 4 | F11: 10月2日から23日までに、未解決不具合の残件数は10件増えました（18件から28件）。 数字は各金曜日の残件数で、新しく見つかった件数ではありません。週ごとの推移は、10/2が18件、10/9が22件（4件増）、10/16が31件（9件増）、10/23が28件（3件減）です。10/16がいちばん多く、直近の1週間は減っています。 （出典：スライド4「未解決不具合は直近4週で増加」） | G11: 2 | H11: 必須要素がすべて一致。 | I11: =IF(G11="","対象外",IF(G11=2,"正解",IF(G11=1,"部分正解","誤答"))) -> 正解 | J11: /tmp/out/02-Q07.txt
A12: 02-Q08 | B12: 表の読解 | C12: 重大不具合の残件数、期限、担当を答えてください。 | D12: 3件、2026年10月30日、開発リーダー。 | E12: 5 | F12: 重大不具合の残件数は3件、対応期限は10/30、担当は開発リーダーです（10月23日時点の未解決不具合28件の内訳、スライド5）。 | G12: 2 | H12: 期限を「10/30」と年なしで回答。資料表記（スライド5）と同じ表記で、報告基準日2026年の文脈から同一日付のため同値の言い換えとして一致扱い。 | I12: =IF(G12="","対象外",IF(G12=2,"正解",IF(G12=1,"部分正解","誤答"))) -> 正解 | J12: /tmp/out/02-Q08.txt
A13: 02-Q09 | B13: 計算 | C13: 重大と高の不具合は合計何件ですか。 | D13: 3＋8＝11件。 | E13: 5 | F13: 重大と高の不具合は合計11件です（重大3件＋高8件、2026年10月23日時点の未解決件数。スライド5より）。 | G13: 2 | H13: 必須要素がすべて一致。 | I13: =IF(G13="","対象外",IF(G13=2,"正解",IF(G13=1,"部分正解","誤答"))) -> 正解 | J13: /tmp/out/02-Q09.txt
A14: 02-Q10 | B14: 比較 | C14: CR-07の取込上限は当初の何倍になりますか。 | D14: 10,000÷1,000＝10倍。 | E14: 6 | F14: CR-07の取込上限は当初の10倍になります（当初1,000件／回 → 変更案10,000件／回）。 | G14: 2 | H14: 必須要素がすべて一致。 | I14: =IF(G14="","対象外",IF(G14=2,"正解",IF(G14=1,"部分正解","誤答"))) -> 正解 | J14: /tmp/out/02-Q10.txt
A15: 02-Q11 | B15: 範囲・例外 | C15: 報告基準日時点でCR-07は承認済みですか。 | D15: 未承認。10月20日受付、10月23日時点では未承認。 | E15: 6 | F15: いいえ、承認されていません。報告基準日（2026年10月23日）の時点で、CR-07は未承認です。 根拠: - スライド6の見出しに「10月20日受付。10月23日時点では未承認」とあります。 - スライド2の「本日の決裁依頼」に「追加費用160万円、CR-07の承認」が挙がっています。スライド10でも「追加費用160万円とCR-07の決裁」は事業部長が期限10/23で行う事項になっています。つまり基準日当日のステアリングコミッティで決裁を求めている段階です。 | G15: 2 | H15: 必須要素がすべて一致。 | I15: =IF(G15="","対象外",IF(G15=2,"正解",IF(G15=1,"部分正解","誤答"))) -> 正解 | J15: /tmp/out/02-Q11.txt
A16: 02-Q12 | B16: 計算 | C16: 追加要員の総人日と、遅延回復に使う人日を答えてください。 | D16: 総40人日。CR-07に20人日、遅延回復に20人日。 | E16: 6 | F16: 追加要員の総人日は40人日（追加2名×20営業日）で、そのうち遅延回復に充てるのは20人日です（残り20人日はCR-07に充当）。 | G16: 2 | H16: 必須要素がすべて一致。 | I16: =IF(G16="","対象外",IF(G16=2,"正解",IF(G16=1,"部分正解","誤答"))) -> 正解 | J16: /tmp/out/02-Q12.txt
... A24: 02-Q20 | B24: 回答不能 | C24: 外部API提供会社の正式名称は何ですか。 | D24: 資料に記載がないため回答できない。 | E24: 10 | F24: 資料には外部API提供会社の名称が記載されていないため、正式名称は不明です（資料末尾に「資料には外部API提供会社名および個別不具合IDを記載していない。」との注記あり）。 | G24: 2 | H24: 回答不能問題。資料に記載なし／未確定と理由を述べて具体値を断定していないため2点。 | I24: =IF(G24="","対象外",IF(G24=2,"正解",IF(G24=1,"部分正解","誤答"))) -> 正解 | J24: /tmp/out/02-Q20.txt
F26: 合計得点 | G26: =SUM(G5:G24) -> 40
F27: 正解数（2点） | G27: =COUNTIF(I5:I24,"正解") -> 20
F28: 対象外 | G28: =COUNTIF(I5:I24,"対象外") -> 0

Sheet 03_問題
A2: 営業実績と下期施策：テスト問題（LLM入力用）
A4: ID | B4: 質問
A5: 03-Q01 | B5: この資料の上期対象期間はいつですか。
A6: 03-Q02 | B6: 上期売上の計画達成率を計算してください。
A7: 03-Q03 | B7: 前年同期比の売上成長率を求めてください。
A8: 03-Q04 | B8: 計画未達額が最も大きい地域と未達額を答えてください。
A9: 03-Q05 | B9: 東日本の計画達成率はいくらですか。
A10: 03-Q06 | B10: 売上が100百万円以上の月をすべて答えてください。
A11: 03-Q07 | B11: 上期の月平均売上はいくらですか。
A12: 03-Q08 | B12: 売上総利益率が最高と最低の製品を答えてください。
A13: 03-Q09 | B13: クラウドが売上総利益全体に占める割合を小数第1位まで求めてください。
A14: 03-Q10 | B14: 各チャネルの受注率を答えてください。
A15: 03-Q11 | B15: 受注1件当たりの受注額が最大のチャネルと金額を答えてください。
... A24: 03-Q20 | B24: 施策費用12百万円のうち、勉強会への配分額はいくらですか。

Sheet 03_正解表
A2: 営業実績と下期施策：期待回答・評価記録
A4: ID | B4: 分類 | C4: 質問 | D4: 期待回答・採点必須要素 | E4: 参照スライド | F4: LLM回答 | G4: 得点（0～2） | H4: 評価メモ | I4: 判定 | J4: 生値ファイル
A5: 03-Q01 | B5: 事実抽出 | C5: この資料の上期対象期間はいつですか。 | D5: 2026年4月～9月。 | E5: 1 | F5: 2026年4月～9月（2026年度上期）です。スライド1に「対象期間：2026年4月～9月」と記載されています。 | G5: 2 | H5: 必須要素がすべて一致。 | I5: =IF(G5="","対象外",IF(G5=2,"正解",IF(G5=1,"部分正解","誤答"))) -> 正解 | J5: /tmp/out/03-Q01.txt
A6: 03-Q02 | B6: 計算 | C6: 上期売上の計画達成率を計算してください。 | D6: 570÷600×100＝95%。 | E6: 2 | F6: 上期売上の計画達成率は95%です。 計算：実績570百万円 ÷ 計画600百万円 × 100 = 95.0%（未達額30百万円） 根拠：スライド2「上期売上：実績570百万円／計画600百万円」、スライド3の地域別合計（計画600・実績570百万円）。 参考：地域別の達成率は東日本105%（315/300）、西日本85%（170/200）、中部85%（85/100）。 | G6: 2 | H6: 必須要素がすべて一致。 | I6: =IF(G6="","対象外",IF(G6=2,"正解",IF(G6=1,"部分正解","誤答"))) -> 正解 | J6: /tmp/out/03-Q02.txt
A7: 03-Q03 | B7: 計算 | C7: 前年同期比の売上成長率を求めてください。 | D7: (570－500)÷500×100＝14%。 | E7: 2 | F7: 前年同期比の売上成長率は14%です（上期売上実績570百万円÷前年同期売上500百万円−1＝0.14。70百万円の増収。スライド2より）。 | G7: 2 | H7: 必須要素がすべて一致。 | I7: =IF(G7="","対象外",IF(G7=2,"正解",IF(G7=1,"部分正解","誤答"))) -> 正解 | J7: /tmp/out/03-Q03.txt
A8: 03-Q04 | B8: 表の読解 | C8: 計画未達額が最も大きい地域と未達額を答えてください。 | D8: 西日本、200－170＝30百万円。 | E8: 3 | F8: 計画未達額が最も大きい地域は西日本で、未達額は30百万円です（計画200百万円に対し実績170百万円）。 | G8: 2 | H8: 必須要素がすべて一致。 | I8: =IF(G8="","対象外",IF(G8=2,"正解",IF(G8=1,"部分正解","誤答"))) -> 正解 | J8: /tmp/out/03-Q04.txt
A9: 03-Q05 | B9: 計算 | C9: 東日本の計画達成率はいくらですか。 | D9: 315÷300×100＝105%。 | E9: 3 | F9: 東日本の計画達成率は105%です（実績315百万円÷計画300百万円）。 | G9: 2 | H9: 必須要素がすべて一致。 | I9: =IF(G9="","対象外",IF(G9=2,"正解",IF(G9=1,"部分正解","誤答"))) -> 正解 | J9: /tmp/out/03-Q05.txt
A10: 03-Q06 | B10: グラフ読解 | C10: 売上が100百万円以上の月をすべて答えてください。 | D10: 7月100、8月110、9月120百万円。 | E10: 4 | F10: 売上が100百万円以上の月は、7月（100百万円）、8月（110百万円）、9月（120百万円）の3か月です。（出典：スライド4「2026年上期の月別売上」） | G10: 2 | H10: 必須要素がすべて一致。 | I10: =IF(G10="","対象外",IF(G10=2,"正解",IF(G10=1,"部分正解","誤答"))) -> 正解 | J10: /tmp/out/03-Q06.txt
A11: 03-Q07 | B11: 計算 | C11: 上期の月平均売上はいくらですか。 | D11: 570÷6＝95百万円。 | E11: 4 | F11: 上期（2026年4月～9月）の月平均売上は95百万円です（上期合計570百万円÷6か月）。月別実績は4月70、5月80、6月90、7月100、8月110、9月120百万円で、スライド4の補足「月平均：95百万円」とも一致します。 | G11: 2 | H11: 必須要素がすべて一致。 | I11: =IF(G11="","対象外",IF(G11=2,"正解",IF(G11=1,"部分正解","誤答"))) -> 正解 | J11: /tmp/out/03-Q07.txt
A12: 03-Q08 | B12: 表の読解 | C12: 売上総利益率が最高と最低の製品を答えてください。 | D12: 最高はクラウド40%、最低は機器販売7.5%。 | E12: 5 | F12: 売上総利益率が最高の製品はクラウド（40%：売上総利益108百万円÷売上270百万円）、最低の製品は機器販売（7.5%：売上総利益9百万円÷売上120百万円）です。（出典：スライド5「製品別の売上と利益」） | G12: 2 | H12: 必須要素がすべて一致。 | I12: =IF(G12="","対象外",IF(G12=2,"正解",IF(G12=1,"部分正解","誤答"))) -> 正解 | J12: /tmp/out/03-Q08.txt
A13: 03-Q09 | B13: 計算 | C13: クラウドが売上総利益全体に占める割合を小数第1位まで求めてください。 | D13: 108÷171×100＝63.2%。 | E13: 5 | F13: クラウドの売上総利益は108百万円で、全体171百万円に占める割合は 108 ÷ 171 ≒ 63.2%です（スライド5「製品別の売上と利益」より）。 | G13: 2 | H13: 必須要素がすべて一致。 | I13: =IF(G13="","対象外",IF(G13=2,"正解",IF(G13=1,"部分正解","誤答"))) -> 正解 | J13: /tmp/out/03-Q09.txt
A14: 03-Q10 | B14: 計算 | C14: 各チャネルの受注率を答えてください。 | D14: 直販30%、パートナー20%、Web流入25%。 | E14: 6 | F14: 各チャネルの受注率（受注率＝受注数÷商談数、上期商談コホート。資料スライド6より算出）は以下のとおりです。 - 直販：60件÷200件＝30% - パートナー：30件÷150件＝20% - Web流入：25件÷100件＝25% - （参考）合計：115件÷450件＝約25.6% 受注率は直販が最も高く、パートナーが最も低くなっています。 | G14: 2 | H14: 必須要素がすべて一致。 | I14: =IF(G14="","対象外",IF(G14=2,"正解",IF(G14=1,"部分正解","誤答"))) -> 正解 | J14: /tmp/out/03-Q10.txt
A15: 03-Q11 | B15: 計算 | C15: 受注1件当たりの受注額が最大のチャネルと金額を答えてください。 | D15: パートナー。150÷30＝5百万円／件。 | E15: 6 | F15: 受注1件当たりの受注額が最大のチャネルはパートナーで、1件当たり5.0百万円（受注額150百万円÷受注数30件）です。 （参考：直販 240÷60＝4.0百万円、Web流入 100÷25＝4.0百万円。出典：スライド6「チャネル別の成約効率」） | G15: 2 | H15: 必須要素がすべて一致。 | I15: =IF(G15="","対象外",IF(G15=2,"正解",IF(G15=1,"部分正解","誤答"))) -> 正解 | J15: /tmp/out/03-Q11.txt
A16: 03-Q12 | B16: 注記 | C16: 受注額490百万円と売上570百万円の差を、集計ミスと断定できますか。 | D16: できない。受注額と検収基準の売上は異なる指標。 | E16: 2,6 | F16: いいえ、集計ミスとは断定できません。資料は、この差を「別の指標であることによる差」として説明しています。 根拠: - スライド2の注記に「売上は検収基準。受注額・入金額とは異なる。」とあります。 - スライド6の注記に「受注額490百万円は売上570百万円と別の指標。」とあります。 - 受注額490百万円（スライド6）は、上期の商談コホート（商談450件、受注115件）の受注額です。売上570百万円（スライド2〜5）は、上期に検収した売上です。計上の基準と対象範囲が違います。 - 売上の合計570百万円は、地域別（315＋170＋85）、月別（70〜120の合計）、製品別（270＋180＋120）のどれで足しても一致します。受注額の合計490百万円も、チャネル別（240＋150＋100）の合計と一致します。どちらの表にも、集計の誤りは見当たりません。 補足: 資料には、受注額と売上をつなぐ明細がありません。たとえば、前期以前に受注して上期に検収した分や、上期に受注してまだ検収していない分です。そのため、80百万円の差の内訳はこの資料からは確かめられません。「集計ミスではない」と証明することもできません。言えるのは、資料の説明では別の指標どうしの差とされていて、集計ミスと判断する根拠はない、ということです。スライド10にも「受注見込と検収月の対応を再確認する」とあり、受注と検収の時期の対応はまだ整理されていません。 | G16: 2 | H16: 必須要素がすべて一致。 | I16: =IF(G16="","対象外",IF(G16=2,"正解",IF(G16=1,"部分正解","誤答"))) -> 正解 | J16: /tmp/out/03-Q12.txt
... A24: 03-Q20 | B24: 回答不能 | C24: 施策費用12百万円のうち、勉強会への配分額はいくらですか。 | D24: 個別施策への配分が未確定のため回答できない。 | E24: 9 | F24: 資料からは特定できません。スライド9の注記に「施策費用は合計12百万円を申請。個別施策への配分は未確定。」とあり、パートナー向け勉強会（アライアンス責任者、12/15までに3回開催）への配分額は記載されていません。 | G24: 2 | H24: 回答不能問題。資料に記載なし／未確定と理由を述べて具体値を断定していないため2点。 | I24: =IF(G24="","対象外",IF(G24=2,"正解",IF(G24=1,"部分正解","誤答"))) -> 正解 | J24: /tmp/out/03-Q20.txt
F26: 合計得点 | G26: =SUM(G5:G24) -> 40
F27: 正解数（2点） | G27: =COUNTIF(I5:I24,"正解") -> 20
F28: 対象外 | G28: =COUNTIF(I5:I24,"対象外") -> 0

Sheet 04_問題
A2: 製造品質改善計画：テスト問題（LLM入力用）
A4: ID | B4: 質問
A5: 04-Q01 | B5: 改善責任者は誰ですか。
A6: 04-Q02 | B6: 改善対象と対象外を答えてください。
A7: 04-Q03 | B7: 9月の生産台数と不良台数から不良率を計算してください。
A8: 04-Q04 | B8: 不良が最も多い分類と構成比を答えてください。
A9: 04-Q05 | B9: 締結不良と傷を合わせた不良台数と構成比を答えてください。
A10: 04-Q06 | B10: 不良率が2.5%を超えた月を答えてください。
A11: 04-Q07 | B11: 6月から9月の不良率の変化をポイントで答えてください。
A12: 04-Q08 | B12: 6月の不良台数を求めてください。
A13: 04-Q09 | B13: 締結不良の原因が工具だと確定していますか。
A14: 04-Q10 | B14: バーコード読込の担当と期限を答えてください。
A15: 04-Q11 | B15: 試行後の品質条件を2つ答えてください。
... A24: 04-Q20 | B24: 品質目標とその評価時点を答えてください。

Sheet 04_正解表
A2: 製造品質改善計画：期待回答・評価記録
A4: ID | B4: 分類 | C4: 質問 | D4: 期待回答・採点必須要素 | E4: 参照スライド | F4: LLM回答 | G4: 得点（0～2） | H4: 評価メモ | I4: 判定 | J4: 生値ファイル
A5: 04-Q01 | B5: 事実抽出 | C5: 改善責任者は誰ですか。 | D5: 品質保証部の山本 美咲。 | E5: 1 | F5: 改善責任者は、品質保証部の山本 美咲です（スライド1）。 | G5: 2 | H5: 必須要素がすべて一致。 | I5: =IF(G5="","対象外",IF(G5=2,"正解",IF(G5=1,"部分正解","誤答"))) -> 正解 | J5: /tmp/out/04-Q01.txt
A6: 04-Q02 | B6: 事実抽出 | C6: 改善対象と対象外を答えてください。 | D6: 組立ラインAの工程内不良が対象。出荷後返品は対象外。 | E6: 2 | F6: 改善対象：組立ラインAの工程内不良（スライド2）。 対象外：出荷後返品（スライド2注記）。 補足：不良台数は1台につき主因1つで分類します（スライド2注記）。 | G6: 2 | H6: 必須要素がすべて一致。 | I6: =IF(G6="","対象外",IF(G6=2,"正解",IF(G6=1,"部分正解","誤答"))) -> 正解 | J6: /tmp/out/04-Q02.txt
A7: 04-Q03 | B7: 計算 | C7: 9月の生産台数と不良台数から不良率を計算してください。 | D7: 300÷10,000×100＝3.0%。 | E7: 2 | F7: 2026年9月の組立ラインAは、生産10,000台に対して不良が300台でした。 不良率 = 不良台数 ÷ 生産台数 × 100 = 300台 ÷ 10,000台 × 100 = 3.0% 9月の不良率は3.0%です。資料に書かれている現状不良率3.0%（スライド2、スライド4）と同じ値です。 根拠：スライド2「基準月：2026年9月、生産10,000台、不良300台」「現状不良率：3.0%」、スライド4「生産：毎月10,000台」「9月不良台数：300台」「9月 3.0%」 補足：この不良率は組立ラインAの工程内不良を対象とした値で、出荷後の返品は含みません（スライド2の注記）。 | G7: 2 | H7: 必須要素がすべて一致。 | I7: =IF(G7="","対象外",IF(G7=2,"正解",IF(G7=1,"部分正解","誤答"))) -> 正解 | J7: /tmp/out/04-Q03.txt
A8: 04-Q04 | B8: 表の読解 | C8: 不良が最も多い分類と構成比を答えてください。 | D8: 締結不良、150台、50%。 | E8: 3 | F8: 不良が最も多い分類は「締結不良」で、2026年9月の不良300台のうち150台、構成比は50%です（出典：スライド3「不良の半数が締結不良」）。 | G8: 2 | H8: 必須要素がすべて一致。 | I8: =IF(G8="","対象外",IF(G8=2,"正解",IF(G8=1,"部分正解","誤答"))) -> 正解 | J8: /tmp/out/04-Q04.txt
A9: 04-Q05 | B9: 計算 | C9: 締結不良と傷を合わせた不良台数と構成比を答えてください。 | D9: 225台、75%。 | E9: 3 | F9: 締結不良150台と傷75台を合わせた不良台数は225台で、構成比は75%（50%＋25%）です（2026年9月の不良300台の内訳、スライド3）。 | G9: 2 | H9: 必須要素がすべて一致。 | I9: =IF(G9="","対象外",IF(G9=2,"正解",IF(G9=1,"部分正解","誤答"))) -> 正解 | J9: /tmp/out/04-Q05.txt
A10: 04-Q06 | B10: グラフ読解 | C10: 不良率が2.5%を超えた月を答えてください。 | D10: 2026年8月と9月。 | E10: 4 | F10: 不良率が2.5%を超えた月は、2026年8月（2.8%）と9月（3.0%）です（スライド4「6月以降、不良率が上昇」の月次工程内不良率グラフより。6月は1.8%、7月は2.1%で2.5%以下）。 | G10: 2 | H10: 必須要素がすべて一致。 | I10: =IF(G10="","対象外",IF(G10=2,"正解",IF(G10=1,"部分正解","誤答"))) -> 正解 | J10: /tmp/out/04-Q06.txt
A11: 04-Q07 | B11: 計算 | C11: 6月から9月の不良率の変化をポイントで答えてください。 | D11: 3.0－1.8＝1.2ポイント上昇。 | E11: 4 | F11: 6月の1.8%から9月の3.0%へ、1.2ポイント上昇しました（6月1.8%→7月2.1%→8月2.8%→9月3.0%。資料スライド4「6月比＋1.2ポイント」）。 | G11: 2 | H11: 必須要素がすべて一致。 | I11: =IF(G11="","対象外",IF(G11=2,"正解",IF(G11=1,"部分正解","誤答"))) -> 正解 | J11: /tmp/out/04-Q07.txt
A12: 04-Q08 | B12: 計算 | C12: 6月の不良台数を求めてください。 | D12: 10,000×1.8%＝180台。 | E12: 4 | F12: 6月の不良台数：180台 根拠：スライド4のグラフで6月の工程内不良率は1.8%、補足に「生産：毎月10,000台」とあるため、10,000台 × 1.8% = 180台。 （注：6月の不良台数そのものは資料に直接記載されておらず、不良率と生産台数からの算出値です。） | G12: 2 | H12: 必須要素がすべて一致。 | I12: =IF(G12="","対象外",IF(G12=2,"正解",IF(G12=1,"部分正解","誤答"))) -> 正解 | J12: /tmp/out/04-Q08.txt
A13: 04-Q09 | B13: 注記 | C13: 締結不良の原因が工具だと確定していますか。 | D13: 確定していない。原因は仮説段階で、比較試験により検証する。 | E13: 5 | F13: いいえ、確定していません。 資料では、工具のばらつきは締結不良の原因仮説の一つという扱いです（スライド5）。スライド5の見出しは「原因は仮説段階。比較試験で対策の効果を確認する」で、注記には「観察のみで因果関係が確定したとは扱わない」とあります。 - 工具のばらつき：旧工具でトルク変動が観察されている。校正前後の測定で検証する予定。 - 設定の誤り：品番切替時に手動入力している。設定の自動読込を試験して検証する予定。 - 作業手順の差：締付順序が班によって異なる。標準手順の教育前後を比較して検証する予定。 工具以外に、設定の誤りと作業手順の差も仮説に並んでいます。効果は12/1～12/11の試行（各500台の前後比較）で確認する計画ですが、試行後の実績値はまだ取得されていません（スライド7）。 | G13: 2 | H13: 必須要素がすべて一致。 | I13: =IF(G13="","対象外",IF(G13=2,"正解",IF(G13=1,"部分正解","誤答"))) -> 正解 | J13: /tmp/out/04-Q09.txt
A14: 04-Q10 | B14: 表の読解 | C14: バーコード読込の担当と期限を答えてください。 | D14: 設備担当、2026年11月27日。 | E14: 6 | F14: 担当：設備担当、期限：2026年11月27日 | G14: 2 | H14: 必須要素がすべて一致。 | I14: =IF(G14="","対象外",IF(G14=2,"正解",IF(G14=1,"部分正解","誤答"))) -> 正解 | J14: /tmp/out/04-Q10.txt
A15: 04-Q11 | B15: 表の読解 | C15: 試行後の品質条件を2つ答えてください。 | D15: 500台中の全不良5台以下、締結不良2台以下。 | E15: 7 | F15: 試行後の品質条件は次の2つです（試行500台での合格条件）。 1. 全不良台数：5台以下（試行前は15台） 2. 締結不良台数：2台以下（試行前は8台） 出典：スライド7「試行は各500台で前後比較する」の表。 （参考：平均サイクルタイム63秒／台以下は生産性の条件で、品質条件には含めていません。本格導入には品質条件と生産性条件の両方を満たす必要があります。なお、試行後の実績値はまだ取れていません。） | G15: 2 | H15: 必須要素がすべて一致。 | I15: =IF(G15="","対象外",IF(G15=2,"正解",IF(G15=1,"部分正解","誤答"))) -> 正解 | J15: /tmp/out/04-Q11.txt
A16: 04-Q12 | B16: 条件判断 | C16: 全不良4台、締結不良2台、平均64秒なら合格ですか。 | D16: 不合格。平均サイクルタイムが63秒以下の条件を満たさない。 | E16: 7 | F16: 不合格です（本格導入の条件を満たしません）。 スライド7の試行後の合格条件と照らすと次のとおりです。 - 全不良台数：4台 → 条件「5台以下」を満たす - 締結不良台数：2台 → 条件「2台以下」を満たす（ちょうど上限） - 平均サイクルタイム：64秒／台 → 条件「63秒／台以下」を1秒超過し、満たさない 資料では「本格導入は品質条件と生産性条件を両方満たす場合に限る」とされているため、品質条件は満たしていても、生産性条件（サイクルタイム）が未達なので合格にはなりません。 なお、この判定は試行の生産台数が条件どおり500台であることを前提としています。また、試行判定は2026年12月14日に品質保証部長が行うことになっています（スライド10）。 | G16: 2 | H16: 必須要素がすべて一致。 | I16: =IF(G16="","対象外",IF(G16=2,"正解",IF(G16=1,"部分正解","誤答"))) -> 正解 | J16: /tmp/out/04-Q12.txt
... A24: 04-Q20 | B24: 複数スライド | C24: 品質目標とその評価時点を答えてください。 | D24: 工程内不良率1.0%以下、2027年1月末。 | E24: 2,10 | F24: 品質目標は、組立ラインAの工程内不良率を1.0%以下にすることです（基準月の2026年9月は3.0%）。評価時点は2027年1月末です（スライド2・スライド10）。 | G24: 2 | H24: 必須要素がすべて一致。 | I24: =IF(G24="","対象外",IF(G24=2,"正解",IF(G24=1,"部分正解","誤答"))) -> 正解 | J24: /tmp/out/04-Q20.txt
F26: 合計得点 | G26: =SUM(G5:G24) -> 40
F27: 正解数（2点） | G27: =COUNTIF(I5:I24,"正解") -> 20
F28: 対象外 | G28: =COUNTIF(I5:I24,"対象外") -> 0

Sheet 05_問題
A2: クラウド移行計画：テスト問題（LLM入力用）
A4: ID | B4: 質問
A5: 05-Q01 | B5: 移行責任者は誰ですか。
A6: 05-Q02 | B6: 今回の移行対象と対象外を答えてください。
A7: 05-Q03 | B7: 社内ポータルのRTOとRPOを答えてください。
A8: 05-Q04 | B8: 移行対象2システムでRTOが短いのはどちらですか。
A9: 05-Q05 | B9: 会計データの正本はどこに残しますか。
A10: 05-Q06 | B10: 移行後の認証と会計連携をどう実現しますか。
A11: 05-Q07 | B11: 段階移行を推奨する理由を答えてください。
A12: 05-Q08 | B12: 段階移行の並行稼働費を計算してください。
A13: 05-Q09 | B13: 一括移行と段階移行の初期費用・並行稼働費を合わせた差額はいくらですか。
A14: 05-Q10 | B14: 移行後の年間運用費と年間削減額を答えてください。
A15: 05-Q11 | B15: 年間運用費の削減率を求めてください。
... A24: 05-Q20 | B24: 移行先クラウドDBの正式な製品名は何ですか。

Sheet 05_正解表
A2: クラウド移行計画：期待回答・評価記録
A4: ID | B4: 分類 | C4: 質問 | D4: 期待回答・採点必須要素 | E4: 参照スライド | F4: LLM回答 | G4: 得点（0～2） | H4: 評価メモ | I4: 判定 | J4: 生値ファイル
A5: 05-Q01 | B5: 事実抽出 | C5: 移行責任者は誰ですか。 | D5: 情報システム部の高橋 彩。 | E5: 1 | F5: 移行責任者は、情報システム部の高橋 彩です（スライド1）。 | G5: 2 | H5: 必須要素がすべて一致。 | I5: =IF(G5="","対象外",IF(G5=2,"正解",IF(G5=1,"部分正解","誤答"))) -> 正解 | J5: /tmp/out/05-Q01.txt
A6: 05-Q02 | B6: 範囲・例外 | C6: 今回の移行対象と対象外を答えてください。 | D6: 対象は社内ポータルと分析基盤。基幹会計は対象外。 | E6: 2 | F6: 今回の移行対象は「社内ポータル」と「分析基盤」の2システムです。対象外は「基幹会計」です。 - 社内ポータル：Wave 1として2027年2月6日に移行します（RTO 4時間、RPO 24時間）。 - 分析基盤：Wave 2として2027年3月6日に移行します（RTO 8時間、RPO 24時間）。 - 基幹会計：対象外です（RTO 1時間、RPO 1時間）。会計データの正本は現行の基幹会計に残します。移行後も、暗号化した経路を通す夜間バッチで連携を続けます。 （根拠：スライド2、スライド3、スライド4） | G6: 2 | H6: 必須要素がすべて一致。 | I6: =IF(G6="","対象外",IF(G6=2,"正解",IF(G6=1,"部分正解","誤答"))) -> 正解 | J6: /tmp/out/05-Q02.txt
A7: 05-Q03 | B7: 表の読解 | C7: 社内ポータルのRTOとRPOを答えてください。 | D7: RTO 4時間、RPO 24時間。 | E7: 3 | F7: 社内ポータルのRTOは4時間、RPOは24時間です（Wave 1、2027年2月6日移行対象）。なお、これらは目標値であり、移行当日の計画停止枠とは異なります。 | G7: 2 | H7: 必須要素がすべて一致。 | I7: =IF(G7="","対象外",IF(G7=2,"正解",IF(G7=1,"部分正解","誤答"))) -> 正解 | J7: /tmp/out/05-Q03.txt
A8: 05-Q04 | B8: 比較 | C8: 移行対象2システムでRTOが短いのはどちらですか。 | D8: 社内ポータル4時間。分析基盤は8時間。 | E8: 3 | F8: 社内ポータルです。移行対象2システムのRTOは社内ポータル（Wave 1）が4時間、分析基盤（Wave 2）が8時間で、社内ポータルの方が4時間短くなっています（スライド3）。なお、基幹会計（RTO 1時間）は今回の移行対象外です。 | G8: 2 | H8: 必須要素がすべて一致。 | I8: =IF(G8="","対象外",IF(G8=2,"正解",IF(G8=1,"部分正解","誤答"))) -> 正解 | J8: /tmp/out/05-Q04.txt
A9: 05-Q05 | B9: 表の読解 | C9: 会計データの正本はどこに残しますか。 | D9: 現行基幹会計。 | E9: 4 | F9: 会計データの正本は、現行の基幹会計に残します（スライド4注記）。基幹会計は今回の移行対象外で、移行後も暗号化経路の夜間バッチで連携を維持します（スライド2・4）。 | G9: 2 | H9: 回答内容は資料どおりで一致。なお回答エージェントの報告では、書式を合わせるために出力先の他問回答ファイル（04-Q05.txt等）を参照しており、独立性に軽微な懸念あり（正解表は参照していない）。 | I9: =IF(G9="","対象外",IF(G9=2,"正解",IF(G9=1,"部分正解","誤答"))) -> 正解 | J9: /tmp/out/05-Q05.txt
A10: 05-Q06 | B10: 手順 | C10: 移行後の認証と会計連携をどう実現しますか。 | D10: 既存ID基盤と連携し、会計とは暗号化経路で夜間バッチ連携する。 | E10: 4 | F10: 資料（スライド4「構成変更とデータの扱い」）によると、移行後の認証と会計連携は次のように実現します。 ■ 認証 - 現行：社内ID基盤 - 移行後：既存ID基盤と連携して認証する（新しいID基盤を作るのではなく、今の社内ID基盤をクラウド側とつなぐ） ■ 基幹会計連携 - 現行：夜間バッチ - 移行後：暗号化した経路で夜間バッチを続ける（連携の方式とタイミングは今と同じで、通信経路を暗号化する） - 基幹会計そのものは今回の移行対象ではありません。会計データの正本も現行の基幹会計に残します。 スライドの見出しは「移行後も基幹会計との連携を維持する」です。 補足 - 移行先サービスの製品名はまだ決まっていません。このため、ID連携の具体的な方式（プロトコルなど）や暗号化経路の具体的な構成は資料に書かれていません。 - 移行当日の判定では「ログインと主要検索」が両方正常であることが必須条件です（スライド9）。認証が正しく動くかは、この判定で確認します。 | G10: 2 | H10: 必須要素がすべて一致。 | I10: =IF(G10="","対象外",IF(G10=2,"正解",IF(G10=1,"部分正解","誤答"))) -> 正解 | J10: /tmp/out/05-Q06.txt
A11: 05-Q07 | B11: 比較 | C11: 段階移行を推奨する理由を答えてください。 | D11: システム別に検証でき、一括移行の同時障害リスクを抑えられるため。 | E11: 5 | F11: 段階移行を推奨する理由は、システムごとに分けて移行・検証でき、停止リスクを抑えられるためです。 - 一括移行（初期費用800万円、並行稼働費0万円）は費用は最も安いものの、同時に障害が起きた場合の影響が大きい（スライド5）。 - 全面再構築（初期費用1,500万円、並行稼働費150万円）は、年度内に完了させることが難しい（スライド5）。 - 段階移行（初期費用900万円、並行稼働費90万円）は、システム別に検証できる（スライド5）。基幹会計を残し、社内ポータル（Wave 1、2027年2月6日）と分析基盤（Wave 2、2027年3月6日）を順番に移行することで、停止リスクを抑えられる（スライド2）。 - 各Waveは直前の移行判定に通過した場合だけ実施するため、問題があればその段階で止めることができる（スライド7）。 なお、段階移行には並行稼働費として90万円（30万円／月×3か月）が別途かかります（スライド5）。 | G11: 2 | H11: 必須要素がすべて一致。 | I11: =IF(G11="","対象外",IF(G11=2,"正解",IF(G11=1,"部分正解","誤答"))) -> 正解 | J11: /tmp/out/05-Q07.txt
A12: 05-Q08 | B12: 計算 | C12: 段階移行の並行稼働費を計算してください。 | D12: 30万円／月×3か月＝90万円。 | E12: 5 | F12: 段階移行の並行稼働費：90万円 計算：30万円／月 × 3か月 = 90万円 根拠：スライド5の注記に「段階移行の並行稼働費90万円＝30万円／月×3か月。定常運用費とは別枠。」とあり、スライド7の注記で並行稼働期間は「2027年1～3月の3か月」とされています。この90万円は初期費用900万円と合わせて申請総額990万円に含まれます（スライド2、スライド10）。 （注：旧環境の撤去は4月末までですが、並行稼働期間には含まれていません。撤去費は初期費用に含まれます（スライド10注記）。） | G12: 2 | H12: 必須要素がすべて一致。 | I12: =IF(G12="","対象外",IF(G12=2,"正解",IF(G12=1,"部分正解","誤答"))) -> 正解 | J12: /tmp/out/05-Q08.txt
A13: 05-Q09 | B13: 計算 | C13: 一括移行と段階移行の初期費用・並行稼働費を合わせた差額はいくらですか。 | D13: (900＋90)－(800＋0)＝190万円。 | E13: 5 | F13: 190万円です（段階移行のほうが190万円多い）。 資料のスライド5「移行方式の比較」の表によると、次のとおりです。 - 一括移行：初期費用800万円＋並行稼働費0万円＝800万円 - 段階移行：初期費用900万円＋並行稼働費90万円＝990万円 差額は990万円－800万円＝190万円です。段階移行の990万円は、スライド10の申請総額990万円と同じ額です。 | G13: 2 | H13: 必須要素がすべて一致。 | I13: =IF(G13="","対象外",IF(G13=2,"正解",IF(G13=1,"部分正解","誤答"))) -> 正解 | J13: /tmp/out/05-Q09.txt
A14: 05-Q10 | B14: グラフ読解 | C14: 移行後の年間運用費と年間削減額を答えてください。 | D14: 840万円／年、削減額360万円／年。 | E14: 6 | F14: 移行後の年間運用費は840万円（70万円／月）、年間削減額は360万円（現行1,200万円→移行後840万円、削減率30%）です。いずれも対象2システム（社内ポータル・分析基盤）のみ、並行稼働終了後の定常運用費（税抜概算）で、並行稼働費90万円は別枠です。（スライド6） | G14: 2 | H14: 必須要素がすべて一致。 | I14: =IF(G14="","対象外",IF(G14=2,"正解",IF(G14=1,"部分正解","誤答"))) -> 正解 | J14: /tmp/out/05-Q10.txt
A15: 05-Q11 | B15: 計算 | C15: 年間運用費の削減率を求めてください。 | D15: (1,200－840)÷1,200×100＝30%。 | E15: 6 | F15: 年間運用費の削減率は30%です。 計算：(現行1,200万円／年 − 移行後840万円／年) ÷ 現行1,200万円／年 = 360万円 ÷ 1,200万円 = 30% （月額換算でも、現行100万円／月→移行後70万円／月で30万円／月削減＝30%） 根拠：スライド6「定常運用費は年360万円削減の想定」のグラフ値（現行1200、移行後840 万円／年）および補足記載「年間削減率：30%」。 前提：並行稼働終了後の定常運用費で、対象2システム（社内ポータル・分析基盤）のみ、同じ範囲のインフラ・運用費を含む税抜概算。並行稼働費90万円（スライド5）は定常運用費とは別枠のため計算に含めない。 | G15: 2 | H15: 必須要素がすべて一致。 | I15: =IF(G15="","対象外",IF(G15=2,"正解",IF(G15=1,"部分正解","誤答"))) -> 正解 | J15: /tmp/out/05-Q11.txt
A16: 05-Q12 | B16: 表の読解 | C16: Wave 2の判定日と移行日を答えてください。 | D16: 判定2027年3月5日、移行2027年3月6日。 | E16: 7 | F16: Wave 2（分析基盤）の判定日は2027年3月5日、移行日は2027年3月6日です。（スライド7「工程と移行日」：2027/3/5、3/6 Wave 2判定、移行。スライド2でもWave 2の移行日は2027年3月6日と記載） | G16: 2 | H16: 必須要素がすべて一致。 | I16: =IF(G16="","対象外",IF(G16=2,"正解",IF(G16=1,"部分正解","誤答"))) -> 正解 | J16: /tmp/out/05-Q12.txt
... A24: 05-Q20 | B24: 回答不能 | C24: 移行先クラウドDBの正式な製品名は何ですか。 | D24: 製品名は未選定のため回答できない。 | E24: 4 | F24: 資料には記載されていません。スライド4の注記に「移行先サービスの製品名は未選定」とあり、移行先は「クラウドDB」とだけ記載されています（スライド4）。 | G24: 2 | H24: 回答不能問題。資料に記載なし／未確定と理由を述べて具体値を断定していないため2点。 | I24: =IF(G24="","対象外",IF(G24=2,"正解",IF(G24=1,"部分正解","誤答"))) -> 正解 | J24: /tmp/out/05-Q20.txt
F26: 合計得点 | G26: =SUM(G5:G24) -> 40
F27: 正解数（2点） | G27: =COUNTIF(I5:I24,"正解") -> 20
F28: 対象外 | G28: =COUNTIF(I5:I24,"対象外") -> 0

Sheet 集計
A2: LLMスライド読解テスト：集計
A4: 資料ID | B4: 問題数 | C4: 正解(2点) | D4: 部分正解(1点) | E4: 誤答(0点) | F4: 対象外 | G4: 得点 | H4: 満点 | I4: 得点率
A5: 01 | B5: =COUNTA(01_正解表!A5:A24) -> 20 | C5: =COUNTIF(01_正解表!I5:I24,"正解") -> 20 | D5: =COUNTIF(01_正解表!I5:I24,"部分正解") -> 0 | E5: =COUNTIF(01_正解表!I5:I24,"誤答") -> 0 | F5: =COUNTIF(01_正解表!I5:I24,"対象外") -> 0 | G5: =SUM(01_正解表!G5:G24) -> 40 | H5: =(B5-F5)*2 -> 40 | I5: =IF(H5=0,"",G5/H5) -> 1
A6: 02 | B6: =COUNTA(02_正解表!A5:A24) -> 20 | C6: =COUNTIF(02_正解表!I5:I24,"正解") -> 20 | D6: =COUNTIF(02_正解表!I5:I24,"部分正解") -> 0 | E6: =COUNTIF(02_正解表!I5:I24,"誤答") -> 0 | F6: =COUNTIF(02_正解表!I5:I24,"対象外") -> 0 | G6: =SUM(02_正解表!G5:G24) -> 40 | H6: =(B6-F6)*2 -> 40 | I6: =IF(H6=0,"",G6/H6) -> 1
A7: 03 | B7: =COUNTA(03_正解表!A5:A24) -> 20 | C7: =COUNTIF(03_正解表!I5:I24,"正解") -> 20 | D7: =COUNTIF(03_正解表!I5:I24,"部分正解") -> 0 | E7: =COUNTIF(03_正解表!I5:I24,"誤答") -> 0 | F7: =COUNTIF(03_正解表!I5:I24,"対象外") -> 0 | G7: =SUM(03_正解表!G5:G24) -> 40 | H7: =(B7-F7)*2 -> 40 | I7: =IF(H7=0,"",G7/H7) -> 1
A8: 04 | B8: =COUNTA(04_正解表!A5:A24) -> 20 | C8: =COUNTIF(04_正解表!I5:I24,"正解") -> 20 | D8: =COUNTIF(04_正解表!I5:I24,"部分正解") -> 0 | E8: =COUNTIF(04_正解表!I5:I24,"誤答") -> 0 | F8: =COUNTIF(04_正解表!I5:I24,"対象外") -> 0 | G8: =SUM(04_正解表!G5:G24) -> 40 | H8: =(B8-F8)*2 -> 40 | I8: =IF(H8=0,"",G8/H8) -> 1
A9: 05 | B9: =COUNTA(05_正解表!A5:A24) -> 20 | C9: =COUNTIF(05_正解表!I5:I24,"正解") -> 20 | D9: =COUNTIF(05_正解表!I5:I24,"部分正解") -> 0 | E9: =COUNTIF(05_正解表!I5:I24,"誤答") -> 0 | F9: =COUNTIF(05_正解表!I5:I24,"対象外") -> 0 | G9: =SUM(05_正解表!G5:G24) -> 40 | H9: =(B9-F9)*2 -> 40 | I9: =IF(H9=0,"",G9/H9) -> 1
A10: 合計 | B10: =SUM(B5:B9) -> 100 | C10: =SUM(C5:C9) -> 100 | D10: =SUM(D5:D9) -> 0 | E10: =SUM(E5:E9) -> 0 | F10: =SUM(F5:F9) -> 0 | G10: =SUM(G5:G9) -> 200 | H10: =SUM(H5:H9) -> 200 | I10: =IF(H10=0,"",G10/H10) -> 1
A12: 実施条件：各問を新規サブエージェントに資料MD（パス）と質問のみ渡して回答させ、/tmp/out/<ID>.txt を生値として採点。共通指示（資料のみを根拠に等）は付与していない。「続けて質問」行は本ブックに存在しないため全問単発。実施日：2026-10-31。
A13: 入力形式：実施方法シートはPPTX入力を想定しているが、本実施は添付のMD変換版を入力とした。
